Workbook
Name DATA1: #REF!
Name DATA2: #REF!
Name DATA3: #REF!
Name DATA4: #REF!
Name TEST0: #REF!
Name TESTHKEY: #REF!
Name TESTKEYS: #REF!
Name TESTVKEY: #REF!

Sheet DISPONIBILIDAD 
A1: CODIGO LAMINA | B1: LAMINA 0,195 VIRGEN | C1: STEEL FORCE | D1: JINTAI | E1: SUXUN | F1: INV. SEM 4 | K1: INVEN INIC SEM | N1: LAM | O1: CONTROL PRODUCCION SEMANA 21 - 2026 | Q1: CANT PROGRAMADA | R1: LUNES | S1: MARTES | T1: MIÉRCOLES | U1: JUEVES | V1: VIERNES | W1: SÁBADO | X1: DOMINGO | Y1: TOTAL SEMANA | AB1: TAPA | AD1: LAMINA | AE1: REFERENCIA LAMINA
A2: 306780 | B2: LAMINA CROM | C2: ='MODELO LAYOUT'!B54 -> 141 | D2: ='MODELO LAYOUT'!F54 -> 0 | E2: ='MODELO LAYOUT'!D54 -> 126 | F2: =C3 -> 267 | K2: =(C3)-G3 -> 267 | N2: MATERIAL | O2: MATERIAL | P2: DESCRIPCIÓN | Q2: TOTAL | R2: 46160 | S2: 46161 | T2: 46162 | U2: 46163 | V2: 46164 | W2: 46165 | X2: 46166 | Y2: UN | AB2: 207189 | AC2: TAPA AGUILA ORIGINAL GENERICA | AD2: 210760 | AE2: LAMINA AGUILA AZUL TIPO D 0.195
C3: =SUM(C2:E2) -> 267 | N3: =IFERROR(VLOOKUP(O3,$AB$2:$AE$80,3,0)," ") -> 212315 | O3: 202732 | P3: =IFERROR(_xlfn.CONCAT(VLOOKUP(O3,[1]CODIGOS!$A$1:$D$750,2,0)," ",O3," ","LINEA ",N3,)," ") -> TAPA COSTEÑITA RET CBARRAS LG 202732 LINEA 212315 | R3: 3663000 | U3: =225*11000 -> 2475000 | V3: =120*11000 -> 1320000 | Y3: =SUM(U3:X3) -> 3795000 | AB3: 207371 | AC3: TAPA AGUILA LIGHT R GENERICA | AD3: 211393 | AE3: LAMINA AGUILA LIGHT TIPO D 0.195 330
A4: CODIGO | B4: INVENTARIO DE LAMINA TERMINADA | C4: COD TAPA | D4: NUMERO LAM | E4: NUMERO PAQ | F4: CONSUMO SEM | G4: (FABRICACION) | H4: PROCESO | K4: INV. INICIAL | L4: CONSUMO REAL | N4: =IFERROR(VLOOKUP(O4,$AB$2:$AE$80,3,0)," ") -> 213995 | O4: 213994 | P4: =IFERROR(_xlfn.CONCAT(VLOOKUP(O4,[1]CODIGOS!$A$1:$D$750,2,0)," ",O4," ","LINEA ",N4,)," ") -> TAPA AGUILA MF 2026 213994 LINEA 213995 | R4: 2376000 | S4: 5907000 | W4: =129*11000 -> 1419000 | X4: =175*11000 -> 1925000 | Y4: =SUM(U4:X4) -> 3344000 | AB4: 211878 | AC4: TAPA AGUILA LIGHT 330 R CI PRECIO 2200 | AD4: 211863 | AE4: LAMINA ÁGUILA LIGHT 330 PS TIPO D 0.195
A5: 210760 | B5: =VLOOKUP(A5,$AD$1:$AE$89,2,0) -> LAMINA AGUILA AZUL TIPO D 0.195 | C5: 207189 | D5: =SUMIF(DATA!$A:$A,$A5,DATA!$B:$B)-SUMIFS(DATA!$B:$B,DATA!$A:$A,$A5,DATA!$E:$E,$L$1)-3760 -> 1165 | E5: =D5/1690 -> 0.68934911 | F5: =+L5/667/1690 -> 0 | K5: =(E5+G5)-F5 -> 0.68934911 | L5: =IFERROR(SUMIF($N$3:$N$38,A5,$Y$3:$Y$39)," ") -> 0 | N5: =IFERROR(VLOOKUP(O5,$AB$2:$AE$80,3,0)," ") -> 212694 | O5: 212703 | P5: =IFERROR(_xlfn.CONCAT(VLOOKUP(O5,[1]CODIGOS!$A$1:$D$750,2,0)," ",O5," ","LINEA ",N5,)," ") -> TAPA CLUB COL TRIGO 330 R 212703 LINEA 212694 | S5: 484000 | T5: 536431 | Y5: =SUM(U5:X5) -> 0 | AB5: 208472 | AC5: TAPA POKER 330R CI | AD5: 210761 | AE5: LAMINA POKER ROJA TIPO D 0.195
A6: 211393 | B6: =VLOOKUP(A6,$AD$1:$AE$89,2,0) -> LAMINA AGUILA LIGHT TIPO D 0.195 330 | C6: 207371 | D6: =SUMIF(DATA!$A:$A,$A6,DATA!$B:$B)-SUMIFS(DATA!$B:$B,DATA!$A:$A,$A6,DATA!$E:$E,$L$1) -> 0 | E6: =D6/1690 -> 0 | F6: =+L6/667/1690 -> 0 | K6: =(E6+G6)-F6 -> 0 | L6: =IFERROR(SUMIF($N$3:$N$38,A6,$Y$3:$Y$39)," ") -> 0 | N6: =IFERROR(VLOOKUP(O6,$AB$2:$AE$80,3,0)," ") -> 213868 | O6: 213867 | P6: =IFERROR(_xlfn.CONCAT(VLOOKUP(O6,[1]CODIGOS!$A$1:$D$750,2,0)," ",O6," ","LINEA ",N6,)," ") -> TAPA TEST 213867 LINEA 213868 | T6: 5709000 | U6: =2255000+935000 -> 3190000 | Y6: =SUM(U6:X6) -> 3190000 | AB6: 212407 | AC6: TAPA PRY OFF CLOVER 320 CC PRECIO 2000 | AD6: 212403 | AE6: LAMINA COSTEÑA BACANA 2000 TP D 0.195
A7: 211863 | B7: =VLOOKUP(A7,$AD$1:$AE$89,2,0) -> LAMINA ÁGUILA LIGHT 330 PS TIPO D 0.195 | C7: 211878 | D7: =SUMIF(DATA!$A:$A,$A7,DATA!$B:$B)-SUMIFS(DATA!$B:$B,DATA!$A:$A,$A7,DATA!$E:$E,$L$1) -> 0 | E7: =D7/1690 -> 0 | F7: =+L7/667/1690 -> 0 | K7: =(E7+G7)-F7 -> 0 | L7: =IFERROR(SUMIF($N$3:$N$38,A7,$Y$3:$Y$39)," ") -> 0 | N7: =IFERROR(VLOOKUP(O7,$AB$2:$AE$80,3,0)," ") -> 213367 | O7: 213361 | P7: =IFERROR(_xlfn.CONCAT(VLOOKUP(O7,[1]CODIGOS!$A$1:$D$750,2,0)," ",O7," ","LINEA ",N7,)," ") -> TAPA CLUB PREMIUM TW ECUADOR 213361 LINEA 213367 | V7: =409*11000 -> 4499000 | W7: =390*11000 -> 4290000 | Y7: =SUM(U7:X7) -> 8789000 | AB7: 211311 | AC7: TAPA NATIVA 330 | AD7: 211691 | AE7: LAMINA NATIVA SUR TIPO D 0.195
A8: 210761 | B8: =VLOOKUP(A8,$AD$1:$AE$89,2,0) -> LAMINA POKER ROJA TIPO D 0.195 | C8: 208472 | D8: =SUMIF(DATA!$A:$A,$A8,DATA!$B:$B)-SUMIFS(DATA!$B:$B,DATA!$A:$A,$A8,DATA!$E:$E,$L$1) -> 886 | E8: =D8/1690 -> 0.52426036 | F8: =+L8/667/1690 -> 0 | K8: =(E8+G8)-F8 -> 0.52426036 | L8: =IFERROR(SUMIF($N$3:$N$38,A8,$Y$3:$Y$39)," ") -> 0 | N8: =IFERROR(VLOOKUP(O8,$AB$2:$AE$80,3,0)," ") -> 213738 | O8: 213735 | P8: =IFERROR(_xlfn.CONCAT(VLOOKUP(O8,[1]CODIGOS!$A$1:$D$750,2,0)," ",O8," ","LINEA ",N8,)," ") -> TAPA RENOVATION POKER 213735 LINEA 213738 | R8: 5027000 | Y8: =SUM(U8:X8) -> 0 | AB8: 208078 | AC8: TAPA COLA & POLA ND LG IMG | AD8: 211672 | AE8: LAMINA COLA & POLA TIPO D 0.195
A9: 211208 | B9: =VLOOKUP(A9,$AD$1:$AE$89,2,0) -> LAMINA PILSEN GENERICA TIP D 0.195 | C9: 211824 | D9: =SUMIF(DATA!$A:$A,$A9,DATA!$B:$B)-SUMIFS(DATA!$B:$B,DATA!$A:$A,$A9,DATA!$E:$E,$L$1) -> 15323 | E9: =D9/1690 -> 9.0668639 | F9: =+L9/667/1690 -> 0 | K9: =(E9+G9)-F9 -> 9.0668639 | L9: =IFERROR(SUMIF($N$3:$N$38,A9,$Y$3:$Y$39)," ") -> 0 | N9: =IFERROR(VLOOKUP(O9,$AB$2:$AE$80,3,0)," ") -> 212315 | O9: 202732 | P9: =IFERROR(_xlfn.CONCAT(VLOOKUP(O9,[1]CODIGOS!$A$1:$D$750,2,0)," ",O9," ","LINEA ",N9,)," ") -> TAPA COSTEÑITA RET CBARRAS LG 202732 LINEA 212315 | W9: =427*11000 -> 4697000 | X9: =172*11000 -> 1892000 | Y9: =SUM(U9:X9) -> 6589000 | AB9: 209630 | AC9: TAPA EVENTO YO ME CUIDO PERU | AD9: 211305 | AE9: LAMINA YO ME CUIDO PERU TIPO D 0.195
A10: 212403 | B10: =VLOOKUP(A10,$AD$1:$AE$89,2,0) -> LAMINA COSTEÑA BACANA 2000 TP D 0.195 | C10: 212407 | D10: =SUMIF(DATA!$A:$A,$A10,DATA!$B:$B)-SUMIFS(DATA!$B:$B,DATA!$A:$A,$A10,DATA!$E:$E,$L$1) -> 6497 | E10: =D10/1690 -> 3.8443787 | F10: =+L10/667/1690 -> 0.42937111 | K10: =(E10+G10)-F10 -> 3.4150076 | L10: =IFERROR(SUMIF($N$3:$N$38,A10,$Y$3:$Y$39)," ") -> 484000 | N10: =IFERROR(VLOOKUP(O10,$AB$2:$AE$80,3,0)," ") -> 213995 | O10: 213994 | P10: =IFERROR(_xlfn.CONCAT(VLOOKUP(O10,[1]CODIGOS!$A$1:$D$750,2,0)," ",O10," ","LINEA ",N10,)," ") -> TAPA AGUILA MF 2026 213994 LINEA 213995 | U10: =98*11000 -> 1078000 | V10: =532*11000 -> 5852000 | W10: =111*11000 -> 1221000 | Y10: =SUM(U10:X10) -> 8151000 | AB10: 212195 | AC10: TAPA YO ME CUIDO PERU ST | AD10: 212127 | AE10: LAMINA YO ME CUIDO PERU ST TIPO D 0.195
A11: 211691 | B11: =VLOOKUP(A11,$AD$1:$AE$89,2,0) -> LAMINA NATIVA SUR TIPO D 0.195 | C11: 211452 | D11: =SUMIF(DATA!$A:$A,$A11,DATA!$B:$B)-SUMIFS(DATA!$B:$B,DATA!$A:$A,$A11,DATA!$E:$E,$L$1) -> 1847 | E11: =D11/1690 -> 1.0928994 | F11: =+L11/667/1690 -> 0 | K11: =(E11+G11)-F11 -> 1.0928994 | L11: =IFERROR(SUMIF($N$3:$N$38,A11,$Y$3:$Y$39)," ") -> 0 | N11: =IFERROR(VLOOKUP(O11,$AB$2:$AE$80,3,0)," ") -> 213637 | O11: 213635 | P11: =IFERROR(_xlfn.CONCAT(VLOOKUP(O11,[1]CODIGOS!$A$1:$D$750,2,0)," ",O11," ","LINEA ",N10,)," ") -> TAPA AGUILA LIGHT PROMO ALFA 213635 LINEA 213995 | R11: 979000 | S11: 4499000 | T11: =440*11000 -> 4840000 | U11: =428*11000 -> 4708000 | Y11: =SUM(U11:X11) -> 4708000 | AB11: 209629 | AC11: TAPA GOLDEN PERU | AD11: 212481 | AE11: LAMINA GOLDEN TIPO D 0.195
A12: 213802 | B12: =VLOOKUP(A12,$AD$1:$AE$89,2,0) -> LAMINA MCHELOB ULTRA NRB 330 TIPO D0.195 | C12: 213801 | D12: =SUMIF(DATA!$A:$A,$A12,DATA!$B:$B)-SUMIFS(DATA!$B:$B,DATA!$A:$A,$A12,DATA!$E:$E,$L$1) -> 0 | E12: =D12/1690 -> 0 | F12: =+L12/667/1690 -> 0 | K12: =(E12+G12)-F12 -> 0 | L12: =IFERROR(SUMIF($N$3:$N$38,A12,$Y$3:$Y$39)," ") -> 0 | N12: =IFERROR(VLOOKUP(O12,$AB$2:$AE$80,3,0)," ") -> 213995 | O12: 213994 | P12: =IFERROR(_xlfn.CONCAT(VLOOKUP(O12,[1]CODIGOS!$A$1:$D$750,2,0)," ",O12," ","LINEA ",N11,)," ") -> TAPA AGUILA MF 2026 213994 LINEA 213637 | S12: 2453000 | T12: =(254*11000)+6550 -> 2800550 | Y12: =SUM(U12:X12) -> 0 | AB12: 209631 | AC12: TAPA CUSQUEÑA CALIDAD PERU | AD12: 211306 | AE12: LAMINA CUSQUEÑA CALIDAD TIPO D 0.195
A13: 212066 | B13: =VLOOKUP(A13,$AD$1:$AE$89,2,0) -> LAMINA CC ROJA TIPO D 0.195 NEW VBI | C13: 212013 | D13: =SUMIF(DATA!$A:$A,$A13,DATA!$B:$B)-SUMIFS(DATA!$B:$B,DATA!$A:$A,$A13,DATA!$E:$E,$L$1) -> 0 | E13: =D13/1690 -> 0 | F13: =+L13/667/1690 -> 0 | K13: =(E13+G13)-F13 -> 0 | L13: =IFERROR(SUMIF($N$3:$N$38,A13,$Y$3:$Y$39)," ") -> 0 | N13: =IFERROR(VLOOKUP(O13,$AB$2:$AE$80,3,0)," ") -> 212019 | O13: 212016 | P13: =IFERROR(_xlfn.CONCAT(VLOOKUP(O13,[1]CODIGOS!$A$1:$D$750,2,0)," ",O13," ","LINEA ",N12,)," ") -> TAPA CLUB COL DRDA R NEW VBI 212016 LINEA 213995 | T13: 121000 | U13: =531*11000 -> 5841000 | V13: =250*11000 -> 2750000 | Y13: =SUM(U13:X13) -> 8591000 | AB13: 212013 | AC13: TAPA CLUB COL ROJA R NEW VBI | AD13: 212066 | AE13: LAMINA CC ROJA TIPO D 0.195 NEW VBI
A14: 212068 | B14: =VLOOKUP(A14,$AD$1:$AE$89,2,0) -> LAMINA CC NEGRA TIPO D 0.195 NEW VBI | C14: 212014 | D14: =SUMIF(DATA!$A:$A,$A14,DATA!$B:$B)-SUMIFS(DATA!$B:$B,DATA!$A:$A,$A14,DATA!$E:$E,$L$1) -> 0 | E14: =D14/1690 -> 0 | F14: =+L14/667/1690 -> 0 | K14: =(E14+G14)-F14 -> 0 | L14: =IFERROR(SUMIF($N$3:$N$38,A14,$Y$3:$Y$39)," ") -> 0 | N14: =IFERROR(VLOOKUP(O14,$AB$2:$AE$80,3,0)," ") -> 213738 | O14: 213735 | P14: =IFERROR(_xlfn.CONCAT(VLOOKUP(O14,[1]CODIGOS!$A$1:$D$750,2,0)," ",O14," ","LINEA ",N13,)," ") -> TAPA RENOVATION POKER 213735 LINEA 212019 | R14: 5962000 | S14: 3729000 | V14: =279*11000 -> 3069000 | W14: =557*11000 -> 6127000 | X14: =167*11000 -> 1837000 | Y14: =SUM(U14:X14) -> 11033000 | AB14: 212014 | AC14: TAPA CLUB COL NG R NEW VBI | AD14: 212068 | AE14: LAMINA CC NEGRA TIPO D 0.195 NEW VBI
A15: 212019 | B15: =VLOOKUP(A15,$AD$1:$AE$89,2,0) -> LAMINA TIPO D 0.195 CLUB COLOM NEW VBI | C15: 212016 | D15: =SUMIF(DATA!$A:$A,$A15,DATA!$B:$B)-SUMIFS(DATA!$B:$B,DATA!$A:$A,$A15,DATA!$E:$E,$L$1) -> 1349 | E15: =D15/1690 -> 0.79822485 | F15: =+L15/667/1690 -> 7.6213373 | K15: =(E15+G15)-F15 -> -6.8231124 | L15: =IFERROR(SUMIF($N$3:$N$38,A15,$Y$3:$Y$39)," ") -> 8591000 | N15: =IFERROR(VLOOKUP(O15,$AB$2:$AE$80,3,0)," ") -> 212315 | O15: 202732 | P15: =IFERROR(_xlfn.CONCAT(VLOOKUP(O15,[1]CODIGOS!$A$1:$D$750,2,0)," ",O15," ","LINEA ",N14,)," ") -> TAPA COSTEÑITA RET CBARRAS LG 202732 LINEA 213738 | T15: 3025000 | Y15: =SUM(U15:X15) -> 0 | AB15: 212016 | AC15: TAPA CLUB COL DRDA R NEW VBI | AD15: 212019 | AE15: LAMINA TIPO D 0.195 CLUB COLOM NEW VBI
A16: 212378 | B16: =VLOOKUP(A16,$AD$1:$AE$89,2,0) -> LAMINA CC OKTOBERFEST TIPOD 0.195 | C16: 212265 | D16: =SUMIF(DATA!$A:$A,$A16,DATA!$B:$B)-SUMIFS(DATA!$B:$B,DATA!$A:$A,$A16,DATA!$E:$E,$L$1) -> 0 | E16: =D16/1690 -> 0 | F16: =+L16/667/1690 -> 0 | K16: =(E16+G16)-F16 -> 0 | L16: =IFERROR(SUMIF($N$3:$N$38,A16,$Y$3:$Y$39)," ") -> 0 | N16: =IFERROR(VLOOKUP(O16,$AB$2:$AE$80,3,0)," ") -> 212403 | O16: 212407 | P16: =IFERROR(_xlfn.CONCAT(VLOOKUP(O16,[1]CODIGOS!$A$1:$D$750,2,0)," ",O16," ","LINEA ",N15,)," ") -> TAPA PRY OFF CLOVER 320 CC PRECIO 2000 212407 LINEA 212315 | R16: 286000 | S16: 7458000 | T16: =651*11000 -> 7161000 | U16: 484000 | Y16: =SUM(U16:X16) -> 484000 | AB16: 212265 | AC16: TAPA CLUB COL DOBLE MALTA 330R FEST | AD16: 212378 | AE16: LAMINA CC OKTOBERFEST TIPOD 0.195
A17: 211217 | B17: =VLOOKUP(A17,$AD$1:$AE$89,2,0) -> LAMINA BUDWEISER TW TIPO D 0.195 | C17: 212080 | D17: =SUMIF(DATA!$A:$A,$A17,DATA!$B:$B)-SUMIFS(DATA!$B:$B,DATA!$A:$A,$A17,DATA!$E:$E,$L$1) -> 1728 | E17: =D17/1690 -> 1.0224852 | F17: =+L17/667/1690 -> 0 | K17: =(E17+G17)-F17 -> 1.0224852 | L17: =IFERROR(SUMIF($N$3:$N$38,A17,$Y$3:$Y$39)," ") -> 0 | N17: =IFERROR(VLOOKUP(O17,$AB$2:$AE$80,3,0)," ") -> 212127 | O17: 212195 | P17: =IFERROR(_xlfn.CONCAT(VLOOKUP(O17,[1]CODIGOS!$A$1:$D$750,2,0)," ",O17," ","LINEA ",N16,)," ") -> TAPA YO ME CUIDO PERU ST 212195 LINEA 212403 | U17: =1089000+781000+1000000 -> 2870000 | V17: =640*11000 -> 7040000 | W17: =150*11000 -> 1650000 | Y17: =SUM(U17:X17) -> 11560000 | AB17: 212080 | AC17: TAPA BUDWEISER RB PRY OFF 250CC | AD17: 211217 | AE17: LAMINA BUDWEISER TW TIPO D 0.195
A18: 211216 | B18: =VLOOKUP(A18,$AD$1:$AE$89,2,0) -> LAMINA PONY ROJA CI TIPO D 0.195 | C18: 208453 | D18: =SUMIF(DATA!$A:$A,$A18,DATA!$B:$B)-SUMIFS(DATA!$B:$B,DATA!$A:$A,$A18,DATA!$E:$E,$L$1) -> 0 | E18: =D18/1690 -> 0 | F18: =+L18/667/1690 -> 0 | K18: =(E18+G18)-F18 -> 0 | L18: =IFERROR(SUMIF($N$3:$N$38,A18,$Y$3:$Y$39)," ") -> 0 | N18: =IFERROR(VLOOKUP(O18,$AB$2:$AE$80,3,0)," ") -> 211209 | O18: 208749 | P18: =IFERROR(_xlfn.CONCAT(VLOOKUP(O18,[1]CODIGOS!$A$1:$D$750,2,0)," ",O18," ","LINEA ",N17,)," ") -> TAPA CORONA 355 MONOLABIAL 208749 LINEA 212127 | R18: 6345249 | Y18: =SUM(U18:X18) -> 0 | AB18: 208453 | AC18: TAPA PONY MALTA GENERICA N CI | AD18: 211216 | AE18: LAMINA PONY ROJA CI TIPO D 0.195
A19: 212315 | B19: =VLOOKUP(A19,$AD$1:$AE$89,2,0) -> LAMINA COSTEÑITA CBARRAS LG TIPOD.0.195 | C19: 202732 | D19: =SUMIF(DATA!$A:$A,$A19,DATA!$B:$B)-SUMIFS(DATA!$B:$B,DATA!$A:$A,$A19,DATA!$E:$E,$L$1) -> 16722 | E19: =D19/1690 -> 9.8946746 | F19: =+L19/667/1690 -> 9.2119621 | G19: 9 | K19: =(E19+G19)-F19 -> 9.6827125 | L19: =IFERROR(SUMIF($N$3:$N$38,A19,$Y$3:$Y$39)," ") -> 10384000 | N19: =IFERROR(VLOOKUP(O19,$AB$2:$AE$80,3,0)," ") -> 213995 | O19: 213994 | P19: =IFERROR(_xlfn.CONCAT(VLOOKUP(O19,[1]CODIGOS!$A$1:$D$750,2,0)," ",O19," ","LINEA ",N18,)," ") -> TAPA AGUILA MF 2026 213994 LINEA 211209 | W19: =500*11000 -> 5500000 | X19: =241*11000 -> 2651000 | Y19: =SUM(U19:X19) -> 8151000 | AB19: 202732 | AC19: TAPA COSTEÑITA RET CBARRAS LG | AD19: 212315 | AE19: LAMINA COSTEÑITA CBARRAS LG TIPOD.0.195
A20: 212604 | B20: =VLOOKUP(A20,$AD$1:$AE$89,2,0) -> LAMINA COSTEÑA ROJA TIPO D0.195 | C20: 212601 | D20: =SUMIF(DATA!$A:$A,$A20,DATA!$B:$B)-SUMIFS(DATA!$B:$B,DATA!$A:$A,$A20,DATA!$E:$E,$L$1) -> 2413 | E20: =D20/1690 -> 1.4278107 | F20: =+L20/667/1690 -> 0 | K20: =(E20+G20)-F20 -> 1.4278107 | L20: =IFERROR(SUMIF($N$3:$N$38,A20,$Y$3:$Y$39)," ") -> 0 | Q20: =SUM(Q3:Q19) -> 0 | R20: =SUBTOTAL(9,R3:R19) -> 24638249 | S20: =SUBTOTAL(9,S3:S19) -> 24530000 | T20: =SUBTOTAL(9,T3:T19) -> 24192981 | U20: =SUBTOTAL(9,U3:U19) -> 20646000 | V20: =SUBTOTAL(9,V3:V19) -> 24530000 | W20: =SUBTOTAL(9,W3:W19) -> 24904000 | X20: =SUBTOTAL(9,X3:X19) -> 8305000 | Y20: =+R20+S20+T20+U20+V20+W20+X20 -> 151746230 | AB20: 212601 | AC20: TAPA COSTEÑA 330R/750R | AD20: 212604 | AE20: LAMINA COSTEÑA ROJA TIPO D0.195
A21: 211209 | B21: =VLOOKUP(A21,$AD$1:$AE$89,2,0) -> LAMINA CORONA MARTE TIPO D 0.195 | C21: 208479 | D21: =SUMIF(DATA!$A:$A,$A21,DATA!$B:$B)-SUMIFS(DATA!$B:$B,DATA!$A:$A,$A21,DATA!$E:$E,$L$1) -> 3061 | E21: =D21/1690 -> 1.8112426 | F21: =+L21/667/1690 -> 0 | K21: =(E21+G21)-F21 -> 1.8112426 | L21: =IFERROR(SUMIF($N$3:$N$38,A21,$Y$3:$Y$39)," ") -> 0 | N21: =IFERROR(VLOOKUP(O23,$AB$2:$AE$80,3,0)," ") | AB21: 208749 | AC21: TAPA CORONA 355 MONOLABIAL | AD21: 211209 | AE21: LAMINA CORONA MARTE TIPO D 0.195
A22: 212321 | B22: =VLOOKUP(A22,$AD$1:$AE$89,2,0) -> LAMINA BBC LG TIPOD.0.195 | C22: 206051 | D22: =SUMIF(DATA!$A:$A,$A22,DATA!$B:$B)-SUMIFS(DATA!$B:$B,DATA!$A:$A,$A22,DATA!$E:$E,$L$1) -> 0 | E22: =D22/1690 -> 0 | F22: =+L22/667/1690 -> 0 | K22: =(E22+G22)-F22 -> 0 | L22: =IFERROR(SUMIF($N$3:$N$38,A22,$Y$3:$Y$39)," ") -> 0 | N22: =IFERROR(VLOOKUP(O24,$AB$2:$AE$80,3,0)," ") | AB22: 206051 | AC22: TAPA BBC LG | AD22: 212321 | AE22: LAMINA BBC LG TIPOD.0.195
A23: 212694 | B23: =VLOOKUP(A23,$AD$1:$AE$89,2,0) -> LAMINA CLUB COLOMBIA TRIGO TIPO D0.195 | C23: 212703 | D23: =SUMIF(DATA!$A:$A,$A23,DATA!$B:$B)-SUMIFS(DATA!$B:$B,DATA!$A:$A,$A23,DATA!$E:$E,$L$1) -> 0 | E23: =D23/1690 -> 0 | F23: =+L23/667/1690 -> 0 | K23: =(E23+G23)-F23 -> 0 | L23: =IFERROR(SUMIF($N$3:$N$38,A23,$Y$3:$Y$39)," ") -> 0 | N23: =IFERROR(VLOOKUP(O25,$AB$2:$AE$80,3,0)," ") | AB23: 212738 | AC23: TAPA AGUILA ORIGINAL NRB | AD23: 212751 | AE23: LAMINA AGUILA ORIGINAL NV TIPO D0.195
A24: 212787 | B24: =VLOOKUP(A24,$AD$1:$AE$89,2,0) -> LAMINA CORONA CERO TIPO D 0,195 | C24: 212812 | D24: =SUMIF(DATA!$A:$A,$A24,DATA!$B:$B)-SUMIFS(DATA!$B:$B,DATA!$A:$A,$A24,DATA!$E:$E,$L$1) -> 1629 | E24: =D24/1690 -> 0.96390533 | F24: =+L24/667/1690 -> 0 | K24: =(E24+G24)-F24 -> 0.96390533 | L24: =IFERROR(SUMIF($N$3:$N$38,A24,$Y$3:$Y$39)," ") -> 0 | N24: =IFERROR(VLOOKUP(O26,$AB$2:$AE$80,3,0)," ") | AB24: 212814 | AC24: TAPA CORONA OLIMPICS | AD24: 212797 | AE24: LAMINA CORONA OLIMPICOS TIPO D 0.195
A25: 213343 | B25: =VLOOKUP(A25,$AD$1:$AE$89,2,0) -> LAMINA AGUILA EL CARIBE D 0.195 | C25: 213340 | D25: =SUMIF(DATA!$A:$A,$A25,DATA!$B:$B)-SUMIFS(DATA!$B:$B,DATA!$A:$A,$A25,DATA!$E:$E,$L$1) -> 629 | E25: =D25/1690 -> 0.37218935 | F25: =+L25/667/1690 -> 0 | K25: =(E25+G25)-F25 -> 0.37218935 | L25: =IFERROR(SUMIF($N$3:$N$38,A25,$Y$3:$Y$39)," ") -> 0 | N25: =IFERROR(VLOOKUP(O27,$AB$2:$AE$80,3,0)," ") | AB25: 212739 | AC25: TAPA AGUILA LIGHT NRB | AD25: 212749 | AE25: LAMINA AGUILA LIGHT NV TIPO D0.195
A26: 213354 | B26: =VLOOKUP(A26,$AD$1:$AE$89,2,0) -> LAMINA REDDS CITRUS UV 0.195 | C26: 213328 | D26: =SUMIF(DATA!$A:$A,$A26,DATA!$B:$B)-SUMIFS(DATA!$B:$B,DATA!$A:$A,$A26,DATA!$E:$E,$L$1) -> 0 | E26: =D26/1690 -> 0 | F26: =+L26/667/1690 -> 0 | K26: =(E26+G26)-F26 -> 0 | L26: =IFERROR(SUMIF($N$3:$N$38,A26,$Y$3:$Y$39)," ") -> 0 | N26: =IFERROR(VLOOKUP(O28,$AB$2:$AE$80,3,0)," ") | Q26: CUSQUEÑA | R26: 3800000 | AB26: 212703 | AC26: TAPA CLUB COL TRIGO 330 R | AD26: 212694 | AE26: LAMINA CLUB COLOMBIA TRIGO TIPO D0.195
A27: 213415 | B27: =VLOOKUP(A27,$AD$1:$AE$89,2,0) -> LAMINA AGUILA GOLES UV TIPO D0.195 | C27: 213413 | D27: =SUMIF(DATA!$A:$A,$A27,DATA!$B:$B)-SUMIFS(DATA!$B:$B,DATA!$A:$A,$A27,DATA!$E:$E,$L$1) -> 0 | E27: =D27/1690 -> 0 | F27: =+L27/667/1690 -> 0 | K27: =(E27+G27)-F27 -> 0 | L27: =IFERROR(SUMIF($N$3:$N$38,A27,$Y$3:$Y$39)," ") -> 0 | N27: =IFERROR(VLOOKUP(O29,$AB$2:$AE$80,3,0)," ") | Q27: YO ME CUIDO | R27: 23900000 | AB27: 212916 | AC27: TAPA AGUILA COPA AMERICA | AD27: 212917 | AE27: LAMINA AGUILA COPA AMERICA TIPO D0.195
A28: 213438 | B28: =VLOOKUP(A28,$AD$1:$AE$89,2,0) -> LAMINA COLA & POLA UV TIPO D0.195 | C28: 213420 | D28: =SUMIF(DATA!$A:$A,$A28,DATA!$B:$B)-SUMIFS(DATA!$B:$B,DATA!$A:$A,$A28,DATA!$E:$E,$L$1) -> 0 | E28: =D28/1690 -> 0 | F28: =+L28/667/1690 -> 0 | K28: =(E28+G28)-F28 -> 0 | L28: =IFERROR(SUMIF($N$3:$N$38,A28,$Y$3:$Y$39)," ") -> 0 | AB28: 213208 | AC28: TAPA TOUR AGUILA 330 | AD28: 213210 | AE28: LAMINA UV TOUR AGUILA TIPO D0.195
A29: 213352 | B29: =VLOOKUP(A29,$AD$1:$AE$89,2,0) -> LAMINA NUTRI MALTA D 0.195 | C29: 213341 | D29: =SUMIF(DATA!$A:$A,$A29,DATA!$B:$B)-SUMIFS(DATA!$B:$B,DATA!$A:$A,$A29,DATA!$E:$E,$L$1) -> 1519 | E29: =D29/1690 -> 0.89881657 | F29: =+L29/667/1690 -> 0 | K29: =(E29+G29)-F29 -> 0.89881657 | L29: =IFERROR(SUMIF($N$3:$N$38,A29,$Y$3:$Y$39)," ") -> 0 | AB29: 213208 | AC29: TAPA TOUR AGUILA 330 | AD29: 213209 | AE29: LAMINA COV TOUR AGUILA TIPO D0.195
A30: 213324 | B30: =VLOOKUP(A30,$AD$1:$AE$89,2,0) -> LAMINA PONY MALTA GO 0.195 | C30: 213321 | D30: =SUMIF(DATA!$A:$A,$A30,DATA!$B:$B)-SUMIFS(DATA!$B:$B,DATA!$A:$A,$A30,DATA!$E:$E,$L$1) -> 0 | E30: =D30/1690 -> 0 | F30: =+L30/667/1690 -> 0 | K30: =(E30+G30)-F30 -> 0 | L30: =IFERROR(SUMIF($N$3:$N$38,A30,$Y$3:$Y$39)," ") -> 0 | AB30: 213146 | AC30: TAPA AGUILA IMPERIAL 330 R | AD30: 213147 | AE30: LAMINA AGUILA IMPERIAL TIPO D0.195
A31: 213482 | B31: =VLOOKUP(A31,$AD$1:$AE$89,2,0) -> LAMINA PILSEN FRASES TIPO D0.195 | C31: 213481 | D31: =SUMIF(DATA!$A:$A,$A31,DATA!$B:$B)-SUMIFS(DATA!$B:$B,DATA!$A:$A,$A31,DATA!$E:$E,$L$1) -> 0 | E31: =D31/1690 -> 0 | F31: =+L31/667/1690 -> 0 | K31: =(E31+G31)-F31 -> 0 | L31: =IFERROR(SUMIF($N$3:$N$38,A31,$Y$3:$Y$39)," ") -> 0 | Q31: 19 YO ME CUIDO | AB31: 212812 | AC31: TAPA CORONA CERO MX | AD31: 212787 | AE31: LAMINA CORONA CERO TIPO D 0,195
A32: 213325 | B32: =VLOOKUP(A32,$AD$1:$AE$89,2,0) -> LAMINA PONY MALTA ANTOJOS 0.195 | C32: 213322 | D32: =SUMIF(DATA!$A:$A,$A32,DATA!$B:$B)-SUMIFS(DATA!$B:$B,DATA!$A:$A,$A32,DATA!$E:$E,$L$1) -> 0 | E32: =D32/1690 -> 0 | F32: =+L32/667/1690 -> 0 | K32: =(E32+G32)-F32 -> 0 | L32: =IFERROR(SUMIF($N$3:$N$38,A32,$Y$3:$Y$39)," ") -> 0 | Q32: 17 CUSQUEÑA | AB32: 213229 | AC32: TAPA COSTEÑA LA VIDA BACANA | AD32: 213237 | AE32: LAMINA COSTEÑA LA VIDA BACANA
A33: 213637 | B33: =VLOOKUP(A33,$AD$1:$AE$89,2,0) -> LAMINA AGUILA LGT PROMO ALFA TIP D 0.195 | C33: 213635 | D33: =SUMIF(DATA!$A:$A,$A33,DATA!$B:$B)-SUMIFS(DATA!$B:$B,DATA!$A:$A,$A33,DATA!$E:$E,$L$1) -> 25460 | E33: =D33/1690 -> 15.065089 | F33: =+L33/667/1690 -> 4.1766099 | K33: =(E33+G33)-F33 -> 10.888479 | L33: =IFERROR(SUMIF($N$3:$N$38,A33,$Y$3:$Y$39)," ") -> 4708000 | AB33: 213340 | AC33: TAPA AGUILA EL CARIBE | AD33: 213356 | AE33: LAMINA AGUILA CARIBE
A34: 213738 | B34: =VLOOKUP(A34,$AD$1:$AE$89,2,0) -> LAMINA POKER RENOVACION | C34: 213735 | D34: =SUMIF(DATA!$A:$A,$A34,DATA!$B:$B)-SUMIFS(DATA!$B:$B,DATA!$A:$A,$A34,DATA!$E:$E,$L$1)-2938 -> 7188 | E34: =D34/1690 -> 4.2532544 | F34: =+L34/667/1690 -> 9.7877097 | G34: 20 | K34: =(E34+G34)-F34 -> 14.465545 | L34: =IFERROR(SUMIF($N$3:$N$38,A34,$Y$3:$Y$39)," ") -> 11033000 | AB34: 213340 | AC34: TAPA AGUILA EL CARIBE | AD34: 213343 | AE34: LAMINA AGUILA EL CARIBE D 0.195
A35: 213732 | B35: =VLOOKUP(A35,$AD$1:$AE$89,2,0) -> LAMINA COSTEÑA BACANA CENTRO TIPO D 0.195 | C35: 213731 | D35: =SUMIF(DATA!$A:$A,$A35,DATA!$B:$B)-SUMIFS(DATA!$B:$B,DATA!$A:$A,$A35,DATA!$E:$E,$L$1) -> 743 | E35: =D35/1690 -> 0.43964497 | F35: =+L35/667/1690 -> 0 | K35: =(E35+G35)-F35 -> 0.43964497 | L35: =IFERROR(SUMIF($N$3:$N$38,A35,$Y$3:$Y$39)," ") -> 0 | AB35: 213328 | AC35: TAPA REDDS CITRUS | AD35: 213354 | AE35: LAMINA REDDS CITRUS UV 0.195
A36: 213868 | B36: =VLOOKUP(A36,$AD$1:$AE$89,2,0) -> LAMINA TAPA TEST CONV TIPO D0.195 | C36: 213867 | D36: =SUMIF(DATA!$A:$A,$A36,DATA!$B:$B)-SUMIFS(DATA!$B:$B,DATA!$A:$A,$A36,DATA!$E:$E,$L$1) -> 400 | E36: =D36/1690 -> 0.23668639 | F36: =+L36/667/1690 -> 2.829946 | K36: =(E36+G36)-F36 -> -2.5932596 | L36: =IFERROR(SUMIF($N$3:$N$38,A36,$Y$3:$Y$39)," ") -> 3190000 | AB36: 213413 | AC36: TAPA AGUILA GOLES | AD36: 213415 | AE36: LAMINA AGUILA GOLES UV TIPO D0.195
A37: 213869 | B37: =VLOOKUP(A37,$AD$1:$AE$89,2,0) -> LAMINA TAPA TEST UV TIPO D0.195 | C37: 213867 | D37: =SUMIF(DATA!$A:$A,$A37,DATA!$B:$B)-SUMIFS(DATA!$B:$B,DATA!$A:$A,$A37,DATA!$E:$E,$L$1) -> 0 | E37: =D37/1690 -> 0 | F37: =+L37/667/1690 -> 0 | K37: =(E37+G37)-F37 -> 0 | L37: =IFERROR(SUMIF($N$3:$N$38,A37,$Y$3:$Y$39)," ") -> 0 | AB37: 213304 | AC37: TAPA CLUB PREMIUM CLASICA | AD37: 213246 | AE37: LAMINA CLUB PREMIUM CLASICA TIPO D 0.195
A38: 211305 | B38: =VLOOKUP(A38,$AD$1:$AE$89,2,0) -> LAMINA YO ME CUIDO PERU TIPO D 0.195 | C38: 209630 | D38: =SUMIF(DATA!$A:$A,$A38,DATA!$B:$B)-SUMIFS(DATA!$B:$B,DATA!$A:$A,$A38,DATA!$E:$E,$L$1) -> 0 | E38: =D38/1690 -> 0 | F38: =+L38/667/1690 -> 0 | K38: =(E38+G38)-F38 -> 0 | L38: =IFERROR(SUMIF($N$3:$N$38,A38,$Y$3:$Y$39)," ") -> 0 | AB38: 213420 | AC38: TAPA COLA & POLA NUEVA IMAGEN | AD38: 213438 | AE38: LAMINA COLA & POLA UV TIPO D0.195
A39: 212127 | B39: =VLOOKUP(A39,$AD$1:$AE$89,2,0) -> LAMINA YO ME CUIDO PERU ST TIPO D 0.195 | C39: 212195 | D39: =SUMIF(DATA!$A:$A,$A39,DATA!$B:$B)-SUMIFS(DATA!$B:$B,DATA!$A:$A,$A39,DATA!$E:$E,$L$1) -> 2393 | E39: =D39/1690 -> 1.4159763 | F39: =+L39/667/1690 -> 10.255227 | K39: =(E39+G39)-F39 -> -8.8392511 | L39: =IFERROR(SUMIF($N$3:$N$38,A39,$Y$3:$Y$39)," ") -> 11560000 | AB39: 213341 | AC39: TAPA NUTRI MALTA | AD39: 213352 | AE39: LAMINA NUTRI MALTA D 0.195
A40: 212481 | B40: =VLOOKUP(A40,$AD$1:$AE$89,2,0) -> LAMINA GOLDEN TIPO D 0.195 | C40: 209629 | D40: =SUMIF(DATA!$A:$A,$A40,DATA!$B:$B)-SUMIFS(DATA!$B:$B,DATA!$A:$A,$A40,DATA!$E:$E,$L$1) -> 0 | E40: =D40/1690 -> 0 | F40: =+L40/667/1690 -> 0 | K40: =(E40+G40)-F40 -> 0 | L40: =IFERROR(SUMIF($N$3:$N$38,A40,$Y$3:$Y$39)," ") -> 0 | AB40: 213321 | AC40: TAPA PONY MALTA GO | AD40: 213324 | AE40: LAMINA PONY MALTA GO 0.195
A41: 211306 | B41: =VLOOKUP(A41,$AD$1:$AE$89,2,0) -> LAMINA CUSQUEÑA CALIDAD TIPO D 0.195 | C41: 209631 | D41: =SUMIF(DATA!$A:$A,$A41,DATA!$B:$B)-SUMIFS(DATA!$B:$B,DATA!$A:$A,$A41,DATA!$E:$E,$L$1) -> 0 | E41: =D41/1690 -> 0 | F41: =+L41/667/1690 -> 0 | K41: =(E41+G41)-F41 -> 0 | L41: =IFERROR(SUMIF($N$3:$N$38,A41,$Y$3:$Y$39)," ") -> 0 | AB41: 213481 | AC41: TAPA PILSEN FRASES | AD41: 213482 | AE41: LAMINA PILSEN FRASES TIPO D0.195
A42: 213246 | B42: =VLOOKUP(A42,$AD$1:$AE$89,2,0) -> LAMINA CLUB PREMIUM CLASICA TIPO D 0.195 | C42: 213304 | D42: =SUMIF(DATA!$A:$A,$A42,DATA!$B:$B)-SUMIFS(DATA!$B:$B,DATA!$A:$A,$A42,DATA!$E:$E,$L$1) -> 1468 | E42: =D42/1690 -> 0.86863905 | F42: =+L42/667/1690 -> 0 | K42: =(E42+G42)-F42 -> 0.86863905 | L42: =IFERROR(SUMIF($N$3:$N$38,A42,$Y$3:$Y$39)," ") -> 0 | AB42: 213349 | AC42: TAPA NUESTRA SIEMBRA | AD42: 213351 | AE42: LAMINA NUESTRA SIEMBRA D 0.195
A43: 213367 | B43: =VLOOKUP(A43,$AD$1:$AE$89,2,0) -> LAMINA CLUB PREMIUM TW ECUADOR D0.195 | C43: 213631 | D43: =SUMIF(DATA!$A:$A,$A43,DATA!$B:$B)-SUMIFS(DATA!$B:$B,DATA!$A:$A,$A43,DATA!$E:$E,$L$1) -> 520 | E43: =D43/1690 -> 0.30769231 | F43: =+L43/667/1690 -> 7.7969891 | G43: 8 | K43: =(E43+G43)-F43 -> 0.51070323 | L43: =IFERROR(SUMIF($N$3:$N$38,A43,$Y$3:$Y$39)," ") -> 8789000 | AB43: 213322 | AC43: TAPA PONY MALTA ANTOJO | AD43: 213325 | AE43: LAMINA PONY MALTA ANTOJOS 0.195
A44: 213807 | B44: =VLOOKUP(A44,$AD$1:$AE$89,2,0) -> LAMINA GENERICA PO ECUADOR CONVENCIONAL | C44: 213805 | D44: =SUMIF(DATA!$A:$A,$A44,DATA!$B:$B)-SUMIFS(DATA!$B:$B,DATA!$A:$A,$A44,DATA!$E:$E,$L$1) -> 0 | E44: =D44/1690 -> 0 | F44: =+L44/667/1690 -> 0 | K44: =(E44+G44)-F44 -> 0 | L44: =IFERROR(SUMIF($N$3:$N$38,A44,$Y$3:$Y$39)," ") -> 0 | AB44: 213635 | AC44: TAPA AGUILA LIGHT PROMO ALFA | AD44: 213637 | AE44: LAMINA AGUILA LGT PROMO ALFA TIP D 0.195
A45: 213364 | B45: =VLOOKUP(A45,$AD$1:$AE$89,2,0) -> LAMINA PILSENER ECUADOR TW TIPO D 0.195 | C45: 213359 | D45: =SUMIF(DATA!$A:$A,$A45,DATA!$B:$B)-SUMIFS(DATA!$B:$B,DATA!$A:$A,$A45,DATA!$E:$E,$L$1) -> 1404 | E45: =D45/1690 -> 0.83076923 | F45: =+L45/667/1690 -> 0 | K45: =(E45+G45)-F45 -> 0.83076923 | L45: =IFERROR(SUMIF($N$3:$N$38,A45,$Y$3:$Y$39)," ") -> 0 | AB45: 213676 | AC45: TAPA CLUB ESMERALDA PROM DTR | AD45: 213679 | AE45: LAMINA CLUB ESMERALDA PROMOCION 0.195
A46: 213885 | B46: =VLOOKUP(A46,$AD$1:$AE$89,2,0) -> LAMINA TIPO D PILSENER MUNDIAL ECUADOR | C46: 213883 | D46: =SUMIF(DATA!$A:$A,$A46,DATA!$B:$B)-SUMIFS(DATA!$B:$B,DATA!$A:$A,$A46,DATA!$E:$E,$L$1) -> 0 | E46: =D46/1690 -> 0 | F46: =+L46/667/1690 -> 0 | K46: =(E46+G46)-F46 -> 0 | L46: =IFERROR(SUMIF($N$3:$N$38,A46,$Y$3:$Y$39)," ") -> 0 | AB46: 213731 | AC46: TAPA PROMOCION COSTENA BACANA CENTRO | AD46: 213732 | AE46: LAMINA COSTEÑA BACANA CENTRO TIPO D 0.195
A47: 213886 | B47: =VLOOKUP(A47,$AD$1:$AE$89,2,0) -> LAMINA TIPO D PILSENER UV MUNDIAL EC | C47: 213883 | D47: =SUMIF(DATA!$A:$A,$A47,DATA!$B:$B)-SUMIFS(DATA!$B:$B,DATA!$A:$A,$A47,DATA!$E:$E,$L$1) -> 0 | E47: =D47/1690 -> 0 | F47: =+L47/667/1690 -> 0 | K47: =(E47+G47)-F47 -> 0 | L47: =IFERROR(SUMIF($N$3:$N$38,A47,$Y$3:$Y$39)," ") -> 0 | AB47: 213735 | AC47: TAPA RENOVATION POKER | AD47: 213738 | AE47: LAMINA POKER RENOVACION
A48: 213239 | B48: =VLOOKUP(A48,$AD$1:$AE$89,2,0) -> LAMINA PILSENER TIPO D 0.195 | C48: 213302 | D48: =SUMIF(DATA!$A:$A,$A48,DATA!$B:$B)-SUMIFS(DATA!$B:$B,DATA!$A:$A,$A48,DATA!$E:$E,$L$1) -> 371 | E48: =D48/1690 -> 0.21952663 | F48: =+L48/667/1690 -> 0 | K48: =(E48+G48)-F48 -> 0.21952663 | L48: =IFERROR(SUMIF($N$3:$N$38,A48,$Y$3:$Y$39)," ") -> 0 | AD48: 213364 | AE48: LAMINA PILSENER ECUADOR TW TIPO D 0.195
A49: 213241 | B49: =VLOOKUP(A49,$AD$1:$AE$89,2,0) -> LAMINA PILSENER LIGHT D 0.195 | C49: 213303 | D49: =SUMIF(DATA!$A:$A,$A49,DATA!$B:$B)-SUMIFS(DATA!$B:$B,DATA!$A:$A,$A49,DATA!$E:$E,$L$1) -> 0 | E49: =D49/1690 -> 0 | F49: =+L49/667/1690 -> 0 | K49: =(E49+G49)-F49 -> 0 | L49: =IFERROR(SUMIF($N$3:$N$38,A49,$Y$3:$Y$39)," ") -> 0 | AB49: 213805 | AC49: TAPA GENERICA PO 0.195 ECUADOR | AD49: 213807 | AE49: LAMINA GENERICA PO ECUADOR CONVENCIONAL
A50: 213351 | B50: =VLOOKUP(A50,$AD$1:$AE$89,2,0) -> LAMINA NUESTRA SIEMBRA D 0.195 | C50: 213349 | D50: =SUMIF(DATA!$A:$A,$A50,DATA!$B:$B)-SUMIFS(DATA!$B:$B,DATA!$A:$A,$A50,DATA!$E:$E,$L$1) -> 0 | E50: =D50/1690 -> 0 | F50: =+L50/667/1690 -> 0 | K50: =(E50+G50)-F50 -> 0 | L50: =IFERROR(SUMIF($N$3:$N$38,A50,$Y$3:$Y$39)," ") -> 0 | AB50: 213302 | AC50: TAPA PILSENER | AD50: 213239 | AE50: LAMINA PILSENER TIPO D 0.195
A51: 213995 | B51: LAMINA AGUILA MF 2026 CONV TIPO D 0,195 | C51: 213994 | D51: =SUMIF(DATA!$A:$A,$A51,DATA!$B:$B)-SUMIFS(DATA!$B:$B,DATA!$A:$A,$A51,DATA!$E:$E,$L$1) -> 310 | E51: =D51/1690 -> 0.18343195 | F51: =+L51/667/1690 -> 17.428564 | K51: =(E51+G51)-F51 -> -17.245132 | L51: =IFERROR(SUMIF($N$3:$N$38,A51,$Y$3:$Y$39)," ") -> 19646000 | N51: =25-18 -> 7 | AB51: 213361 | AC51: TAPA CLUB PREMIUM TW ECUADOR | AD51: 213367 | AE51: LAMINA CLUB PREMIUM TW ECUADOR D0.195
A52: 213996 | B52: LAMINA AGUILA MF 2026 UV TIPO D 0,195 | C52: 213994 | D52: =SUMIF(DATA!$A:$A,$A52,DATA!$B:$B)-SUMIFS(DATA!$B:$B,DATA!$A:$A,$A52,DATA!$E:$E,$L$1) -> 8602 | E52: =D52/1690 -> 5.0899408 | F52: =+L52/667/1690 -> 0 | K52: =(E52+G52)-F52 -> 5.0899408 | L52: =IFERROR(SUMIF($N$3:$N$38,A52,$Y$3:$Y$39)," ") -> 0 | AB52: 202918 | AC52: TAPA PONY MALTA TW LG | AD52: 206890 | AE52: LAMINA PONY MALTA TW
D53: =SUM(D5:D52) -> 103627 | E53: =SUM(E5:E52) -> 61.317751 | F53: =SUM(F5:F52) -> 69.537716 | K53: =SUM(K5:K52) -> 28.780035 | AB53: 208472 | AC53: TAPA POKER 330R CI | AD53: 202737 | AE53: LAMINA POKER 330/750R TIPO A LG
AB54: 202732 | AC54: TAPA COSTEÑITA RET CBARRAS LG | AD54: 207301 | AE54: LAMINA COSTEÑITA TIPO D
AB55: 208472 | AC55: TAPA POKER 330R CI | AD55: 208477 | AE55: LAMINA POKER ROJA RET LG TIPO D 0,17
AB56: 204340 | AC56: TAPA REDDS 330R LG FASE II | AD56: 204388 | AE56: LAMINA REDDS TIPO D LG FASE II
AD57: 206458 | AE57: LAMINA CLUB PREMIUM RET TIPO D 0,17 ECU
AB58: 209957 | AC58: TAPA PACIFICO CLARA PERU | AD58: 209962 | AE58: LAMINA PACIFICO PERU
AB59: 210125 | AC59: TAPA ESPIGA POKER PURA MALTA 330 NR BBC | AD59: 210128 | AE59: LAMINA POKER BBC PURAMALTA TIPO D 0.17
AB60: 213172 | AC60: TAPA SALVA VIDAS HONDURAS | AD60: 213174 | AE60: LAMINA SALVA VIDAS TIPO D0.17
AB61: 213302 | AC61: TAPA PILSENER | AD61: 213240 | AE61: LAMINA PILSENER TIPO D 0.17
AB62: 213303 | AC62: TAPA PILSENER LIGHT | AD62: 213242 | AE62: LAMINA PILSENER LIGHT D 0.17
AB63: 213304 | AC63: TAPA CLUB PREMIUM CLASICA | AD63: 213245 | AE63: LAMINA CLUB PREMIUM CLASICA TIPO D 0.17
AB64: 213303 | AC64: TAPA PILSENER LIGHT | AD64: 213241 | AE64: LAMINA PILSENER LIGHT D 0.195
AB65: 213801 | AC65: TAPA MCHELOB ULTRA NRB 330 | AD65: 213802 | AE65: LAMINA MCHELOB ULTRA NRB 330 TIPO D0.195
AB66: 213867 | AC66: TAPA TEST | AD66: 213868 | AE66: LAMINA TAPA TEST CONV TIPO D0.195
AB67: 213867 | AC67: TAPA TEST | AD67: 213869 | AE67: LAMINA TAPA TEST UV TIPO D0.195
AB68: 213883 | AC68: TAPA PILSENER MUNDIAL ECUADOR | AD68: 213885 | AE68: LAMINA TIPO D PILSENER MUNDIAL ECUADOR
AB69: 213883 | AC69: TAPA PILSENER MUNDIAL ECUADOR | AD69: 213886 | AE69: LAMINA TIPO D PILSENER UV MUNDIAL EC
... AB74: 213994 | AC74: TAPA AGUILA MF 2026 213994 LINEA 213995 | AD74: 213996 | AE74: LAMINA AGUILA MF 2026 UV TIPO D 0,195

Sheet MODELO LAYOUT
AE1: SALIDA DE MONTACARGAS | CI1: LAMINA | CJ1: TAPA | CK1: DESCRIPCION | CL1: CONSUMO | CM1: DESCRIPCION CONSUMO | CN1: CODIGO | CO1: CANTIDAD | CP1: =AI15 -> 0 | CQ1: =AJ15 -> 0 | CR1: =AK15 -> 0 | CS1: =AL15 -> 0 | CT1: =AM15 -> 0 | CU1: =AN15 -> 0 | CV1: =AO15 -> 0 | CW1: =AP15 -> 0 | ... DN1: =BG15 -> 0
CI2: 211749 | CJ2: N/A | CK2: LAM BASE BLANCA LACA OXY TIPO 0.195 | CL2: N/A | CM2: N/A | CN2: {=TRANSPOSE(CP1:EF1)} -> 0 | CO2: {=TRANSPOSE(CP2:EF2)} -> 0 | CP2: =AI14 -> 0 | CQ2: =AJ14 -> 0 | CR2: =AK14 -> 0 | CS2: =AL14 -> 0 | CT2: =AM14 -> 0 | CU2: =AN14 -> 0 | CV2: =AO14 -> 0 | CW2: =AP14 -> 0 | ... DN2: =BG14 -> 0
CI3: 211747 | CJ3: N/A | CK3: LAM SIZING ALUM LACA OXY TIPO D 0.195 | CL3: N/A | CM3: N/A | CN3: 0 | CO3: 0
A4: BAÑOS HOMBRES | D4: ALMACEN DE BASES Y RECUBRIMIENTOS BT04 | K4: ALMACEN DE BASES Y RECUBRIMIENTOS BT08 | S4: CUARTO DE GANCHOS | W4: CUARTO DE LUBRICANTES | AI4: CUARTO DE COMPRESORES | CI4: 210656 | CJ4: N/A | CK4: LAMINA GEN BASE BLANCA LACADA TIPO D 0.195 | CL4: N/A | CM4: N/A | CN4: 0 | CO4: 0 | CP4: =AI21 -> 0 | CQ4: =AJ21 -> 0 | CR4: =AK21 -> 0 | CS4: =AL21 -> 0 | CT4: =AM21 -> 0 | CU4: =AN21 -> 0 | CV4: =AO21 -> 0 | CW4: =AP21 -> 0 | ... DN4: =BG21 -> 0
AI5: BODEGA DE MOTORES | AM5: CUARTO DE PLANCHAS | AQ5: ALMACEN DE TINTAS | AU5: CENTRO DE CONFIABILIDAD | BH5: LABORATORIO | BR5: CENTRO DE ACOPIO 1 | BZ5: SALIDA EMERGENCIA | CI5: 212037 | CJ5: N/A | CK5: BASE DORADA LACADA 0.195 | CL5: N/A | CM5: N/A | CN5: 0 | CO5: 0 | CP5: =AI20 -> 0 | CQ5: =AJ20 -> 0 | CR5: =AK20 -> 0 | CS5: =AL20 -> 0 | CT5: =AM20 -> 0 | CU5: =AN20 -> 0 | CV5: =AO20 -> 0 | CW5: =AP20 -> 0 | ... DN5: =BG20 -> 0
A6: BAÑOS MUJERES | D6: ALMACEN DE REPUESTOS | P6: CUARTO DE RODILLOS | CI6: 212357 | CJ6: N/A | CK6: LAMINA LACADA BBC LG TIPO D0.195 | CL6: N/A | CM6: N/A | CN6: 0 | CO6: 0
CI7: 210654 | CJ7: N/A | CK7: LAMINA GEN LACADA TIPO D 0,195 | CL7: N/A | CM7: N/A | CN7: 0 | CO7: 0 | CP7: =BJ19 -> 0 | CQ7: =BK19 -> 213732 | CR7: =BL19 -> 213637 | CS7: =BM19 -> 213868 | CT7: =BN19 -> 211691
CI8: 210655 | CJ8: N/A | CK8: LAMINA GEN LACADA SIZING TIPO D 0,195 | CL8: N/A | CM8: N/A | CN8: 0 | CO8: 0 | CP8: =BJ18 -> 0 | CQ8: =BK18 -> 743 | CR8: =BL18 -> 974 | CS8: =BM18 -> 400 | CT8: =BN18 -> 1847
AI9: 1 | AJ9: 2 | AK9: 3 | AL9: 4 | AM9: 5 | AN9: 6 | AO9: 7 | AP9: 8 | AQ9: 9 | AR9: 10 | AS9: 11 | AT9: 12 | AU9: 13 | AV9: 14 | AW9: 15 | AX9: 16 | AY9: 17 | AZ9: 18 | BA9: 19 | BB9: 20 | BC9: 21 | BE9: 22 | BF9: 23 | BG9: 24 | BJ9: 25 | BK9: 26 | BL9: 27 | BM9: 28 | BN9: 29 | BU9: 32 | BV9: 33 | BW9: 34 | BX9: 35 | BY9: 36 | CG9: ENFERMERIA | CI9: 211671 | CJ9: N/A | CK9: LAMINA BASE AGUILA LACA TIPO D 0.195 | CL9: N/A | CM9: N/A | CN9: 0 | CO9: 0
AR10: =+AQ15 -> 0 | AU10: =9*1548 -> 13932 | AV10: 640 | AW10: 2313 | AX10: =1655+1300 -> 2955 | AY10: 1694 | AZ10: 371 | BA10: 310 | BK10: 743 | BL10: 974 | BM10: 400 | BQ10: VOLTEADOR DE LAMINA | BU10: =550 -> 550 | BX10: =1688+1660+1639 -> 4987 | CB10: LINEA DE REVISION | CI10: 213677 | CJ10: N/A | CK10: LAMINA LACADA SIZING PROM TIPO D 0.195 | CL10: N/A | CM10: N/A | CN10: 0 | CO10: 0 | CP10: =BJ25 -> 0 | CQ10: =BK25 -> 0 | CR10: =BL25 -> 0 | CS10: =BM25 -> 0 | CT10: =BN25 -> 0
B11: 3 | C11: 3 | E11: MACULATURA | F11: =SUM(BR13:BR18) -> 110 | BB11: 140 | BN11: 1306 | BX11: =1670+1656+1681 -> 5007 | CI11: 206454 | CJ11: N/A | CK11: LAM BASE BLANCA LACADA TIPO D 0,17 | CL11: N/A | CM11: N/A | CN11: 0 | CO11: 0 | CP11: =BJ24 -> 0 | CQ11: =BK24 -> 0 | CR11: =BL24 -> 0 | CS11: =BM24 -> 0 | CT11: =BN24 -> 0
B12: 2 | C12: 3 | I12: ZONA DE DESTAPE | R12: SACMI 1 - 2 | W12: SACMI 3 - 4 | BC12: =165 -> 165 | BN12: 541 | BX12: =1672+1642+1691 -> 5005 | CI12: 211746 | CJ12: N/A | CK12: LAM SIZING ALUM LACA OXY TIPO D 0.17 | CL12: N/A | CM12: N/A | CN12: 0 | CO12: 0
B13: 3 | C13: 3 | I13: 5 | J13: 1 | K13: 1 | L13: 1 | M13: 1 | N13: 1 | O13: 1 | P13: 1 | BQ13: M | BR13: 15 | BX13: 1663 | CI13: 207530 | CJ13: N/A | CK13: LAM GEN BASE AGUILA LACA TIPO D LG 0.17 | CL13: N/A | CM13: N/A | CN13: 0 | CO13: 0 | CP13: =BU19 -> 210655 | CQ13: =BV19 -> 0 | CR13: =BW19 -> 0 | CS13: =BX19 -> 213677 | CT13: =BY19 -> 0
B14: 1 | C14: 3 | R14: CODIGO | S14: PRODUCTO | T14: INVENTARIO | U14: ACUMULADO | V14: INVENTARIO ACTUAL | W14: CODIGO | X14: PRODUCTO | Y14: INVENTARIO | Z14: ACUMULADO | AA14: INVENTARIO ACTUAL | AI14: =SUM(AI10:AI13) -> 0 | AJ14: =SUM(AJ10:AJ13) -> 0 | AK14: =SUM(AK10:AK13) -> 0 | AL14: =SUM(AL10:AL13) -> 0 | AM14: =SUM(AM10:AM13) -> 0 | AN14: =SUM(AN10:AN13) -> 0 | AO14: =SUM(AO10:AO13) -> 0 | AP14: =SUM(AP10:AP13) -> 0 | ... BC14: =SUM(BC10:BC13) -> 165 | BE14: =SUM(BE10:BE13) -> 0 | BF14: =SUM(BF10:BF13) -> 0 | BG14: =SUM(BG10:BG13) -> 0 | BQ14: L1 | BR14: 20 | CI14: 207235 | CJ14: N/A | CK14: LAM GENERICA BASE DORADA AGUILA LIGHT | CL14: N/A | CM14: N/A | CN14: 213677 | CO14: 13932 | CP14: =BU18 -> 550 | CQ14: =BV18 -> 0 | CR14: =BW18 -> 0 | CS14: =BX18 -> 16662 | CT14: =BY18 -> 0
B15: 2 | C15: 3 | I15: NOTAS RAPIDAS | R15: =AY77 -> 213996 | S15: =VLOOKUP(R15,CI:CM,3,0) -> LAMINA AGUILA MF 2026 UV TIPO D 0,195 | T15: =SUMIF($CN:$CN,R15,$CO:$CO) -> 8602 | V15: =T15-((U15*11000)/675) -> 8602 | W15: =AY78 -> 213637 | X15: =VLOOKUP(W15,CI:CM,3,0) -> LAMINA AGUILA LGT PROMO ALFA TIP D 0.195 | Y15: =SUMIF($CN:$CN,W15,$CO:$CO) -> 25460 | AA15: =Y15-((Z15*11000)/667) -> 25460 | AU15: 213677 | AV15: 212037 | AW15: 211671 | AX15: 211749 | AY15: 210655 | AZ15: 213239 | BA15: 213995 | BB15: 212315 | BC15: 210760 | BQ15: L2 | BR15: 25 | CI15: 207542 | CJ15: N/A | CK15: LAM GEN SIZING T/RENTE LACATIP A LG 0.17 | CL15: N/A | CM15: N/A | CN15: 212037 | CO15: 640
B16: 3 | C16: 1 | U16: NUMERO DE CAJAS | Z16: NUMERO DE CAJAS | AI16: =IFERROR(VLOOKUP(AI15,$CI:$CM,3,0)," ") | AJ16: =IFERROR(VLOOKUP(AJ15,$CI:$CM,3,0)," ") | AK16: =IFERROR(VLOOKUP(AK15,$CI:$CM,3,0)," ") | AL16: =IFERROR(VLOOKUP(AL15,$CI:$CM,3,0)," ") | AM16: =IFERROR(VLOOKUP(AM15,$CI:$CM,3,0)," ") | AN16: =IFERROR(VLOOKUP(AN15,$CI:$CM,3,0)," ") | AO16: =IFERROR(VLOOKUP(AO15,$CI:$CM,3,0)," ") | AP16: =IFERROR(VLOOKUP(AP15,$CI:$CM,3,0)," ") | ... BC16: =IFERROR(VLOOKUP(BC15,$CI:$CM,3,0)," ") -> LAMINA AGUILA AZUL TIPO D 0.195 | BE16: =IFERROR(VLOOKUP(BE15,$CI:$CM,3,0)," ") | BF16: =IFERROR(VLOOKUP(BF15,$CI:$CM,3,0)," ") | BG16: =IFERROR(VLOOKUP(BG15,$CI:$CM,3,0)," ") | BQ16: L2 | BR16: 15 | CI16: 206453 | CJ16: N/A | CK16: LAMINA LACADA TIPO D LG 0,17 | CL16: N/A | CM16: N/A | CN16: 211671 | CO16: 2313 | CP16: =BU25 -> 0 | CQ16: =BV25 -> 0 | CR16: =BW25 -> 0 | CS16: =BX25 -> 0 | CT16: =BY25 -> 212037
U17: =+((V15*667)/11000) -> 521.594 | Z17: =+((AA15*667)/11000) -> 1543.8018 | AV17: SUXUN | AW17: JINTAI | AX17: SUXUN | AY17: SUXUN | AZ17: SUXUN | BB17: STEEL FORCE | BC17: STEEL FORCE | BQ17: L3 | BR17: 20 | CI17: 207544 | CJ17: N/A | CK17: LAMINA LACADA TIPO A LG 0,17 | CL17: N/A | CM17: N/A | CN17: 211749 | CO17: 2955 | CP17: =BU24 -> 0 | CQ17: =BV24 -> 0 | CR17: =BW24 -> 0 | CS17: =BX24 -> 0 | CT17: =BY24 -> 725
AV18: CLUB COLOMBIA MALA IMPRESION | AW18: COLA Y POLA | AX18: BASE BEIGE | AY18: PILSENER LACADA + SIZING | AZ18: PILSENER | BB18: COSTEÑITA CB | BC18: ÁGUILA ORIGINAL | BJ18: =SUM(BJ10:BJ17) -> 0 | BK18: =SUM(BK10:BK17) -> 743 | BL18: =SUM(BL10:BL17) -> 974 | BM18: =SUM(BM10:BM17) -> 400 | BN18: =SUM(BN10:BN17) -> 1847 | BQ18: L3 | BR18: 15 | BU18: =SUM(BU10:BU17) -> 550 | BV18: =SUM(BV10:BV17) -> 0 | BW18: =SUM(BW10:BW17) -> 0 | BX18: =SUM(BX10:BX17) -> 16662 | BY18: =SUM(BY10:BY17) -> 0 | CI18: 207532 | CJ18: N/A | CK18: LAM BASE DORADA SIZINGLACA TIPO D 0.17 | CL18: N/A | CM18: N/A | CN18: 210655 | CO18: 1694
R19: SACMI 5 - 6 | W19: SACMI 7 - 8 | BK19: 213732 | BL19: 213637 | BM19: 213868 | BN19: 211691 | BQ19: MEDIDA MACULATURA | BU19: 210655 | BX19: 213677 | CI19: 206455 | CJ19: N/A | CK19: LAM GEN SIZING T/RENTE LACA TIPO D LG 0.17 | CL19: N/A | CM19: N/A | CN19: 213239 | CO19: 371 | CP19: =BQ32 -> 0 | CQ19: =BR32 -> 0 | CR19: =BS32 -> 0 | CS19: =BT32 -> 211209 | CT19: =BU32 -> 206454 | CU19: =BV32 -> 206453 | CV19: =BW32 -> 207544 | CW19: =BX32 -> 206455 | CX19: =BY32 -> 210654
AW20: 480 | AY20: 1690 | AZ20: =1558+1680+1680 -> 4918 | BJ20: =IFERROR(VLOOKUP(BJ19,$CI:$CM,3,0)," ") | BK20: =IFERROR(VLOOKUP(BK19,$CI:$CM,3,0)," ") -> LAMINA COSTEÑA BACANA CENTRO TIPO D 0.195 | BL20: =IFERROR(VLOOKUP(BL19,$CI:$CM,3,0)," ") -> LAMINA AGUILA LGT PROMO ALFA TIP D 0.195 | BM20: =IFERROR(VLOOKUP(BM19,$CI:$CM,3,0)," ") -> LAMINA TAPA TEST CONV TIPO D0.195 | BN20: =IFERROR(VLOOKUP(BN19,$CI:$CM,3,0)," ") -> LAMINA NATIVA SUR TIPO D 0.195 | BU20: =IFERROR(VLOOKUP(BU19,$CI:$CM,3,0)," ") -> LAMINA GEN LACADA SIZING TIPO D 0,195 | BV20: =IFERROR(VLOOKUP(BV19,$CI:$CM,3,0)," ") | BW20: =IFERROR(VLOOKUP(BW19,$CI:$CM,3,0)," ") | BX20: =IFERROR(VLOOKUP(BX19,$CI:$CM,3,0)," ") -> LAMINA LACADA SIZING PROM TIPO D 0.195 | BY20: =IFERROR(VLOOKUP(BY19,$CI:$CM,3,0)," ") | CI20: 206050 | CJ20: N/A | CK20: LAM BASE BAIGE | CL20: N/A | CM20: N/A | CN20: 213995 | CO20: 310 | CP20: =BQ31 -> 0 | CQ20: =BR31 -> 0 | CR20: =BS31 -> 0 | CS20: =BT31 -> 218 | CT20: =BU31 -> 452 | CU20: =BV31 -> 1176 | CV20: =BW31 -> 4207 | CW20: =BX31 -> 6127 | CX20: =BY31 -> 9553
R21: CODIGO | S21: PRODUCTO | T21: INVENTARIO | U21: ACUMULADO | V21: INVENTARIO ACTUAL | W21: CODIGO | X21: PRODUCTO | Y21: INVENTARIO | Z21: ACUMULADO | AA21: INVENTARIO ACTUAL | AW21: 212037 | AY21: 207544 | AZ21: 210656 | BK21: STEEL FORCE | BL21: STEEL FORCE | BM21: JINTAI | BN21: JINTAI | BU21: SUXUN | BX21: SUXUN | CI21: 210760 | CJ21: 207189 | CK21: LAMINA AGUILA AZUL TIPO D 0.195 | CL21: 210655 | CM21: =VLOOKUP(CL21,$CI$2:$CK$20,3,0) -> LAMINA GEN LACADA SIZING TIPO D 0,195 | CN21: 212315 | CO21: 140
R22: =AY79 -> 213738 | S22: =VLOOKUP(R22,CI:CM,3,0) -> LAMINA POKER RENOVACION | T22: =SUMIF($CN:$CN,R22,$CO:$CO) -> 10126 | V22: =T22-((U22*11000)/667) -> 10126 | W22: =AY80 -> 212403 | X22: =VLOOKUP(W22,CI:CM,3,0) -> LAMINA COSTEÑA BACANA 2000 TP D 0.195 | Y22: =SUMIF($CN:$CN,W22,$CO:$CO) -> 6497 | AA22: =Y22-((Z22*11000)/667) -> 6497 | AI22: =IFERROR(VLOOKUP(AI21,$CI:$CM,3,0)," ") | AJ22: =IFERROR(VLOOKUP(AJ21,$CI:$CM,3,0)," ") | AK22: =IFERROR(VLOOKUP(AK21,$CI:$CM,3,0)," ") | AL22: =IFERROR(VLOOKUP(AL21,$CI:$CM,3,0)," ") | AM22: =IFERROR(VLOOKUP(AM21,$CI:$CM,3,0)," ") | AN22: =IFERROR(VLOOKUP(AN21,$CI:$CM,3,0)," ") | AO22: =IFERROR(VLOOKUP(AO21,$CI:$CM,3,0)," ") | AP22: =IFERROR(VLOOKUP(AP21,$CI:$CM,3,0)," ") | ... BC22: =IFERROR(VLOOKUP(BC21,$CI:$CM,3,0)," ") | BE22: =IFERROR(VLOOKUP(BE21,$CI:$CM,3,0)," ") | BF22: =IFERROR(VLOOKUP(BF21,$CI:$CM,3,0)," ") | BG22: =IFERROR(VLOOKUP(BG21,$CI:$CM,3,0)," ") | BK22: COSTEÑA BACANA CENTRO | BL22: LIGHT | BM22: TEST | BN22: NATIVA | BU22: LACADA ALUMINAZADA PARA ÁGUILA | BX22: BASE DORADA | CI22: 211860 | CJ22: 211877 | CK22: LAMINA ÁGUILA 330 PS TIPO D 0.195 | CL22: 210655 | CM22: =VLOOKUP(CL22,$CI$2:$CK$20,3,0) -> LAMINA GEN LACADA SIZING TIPO D 0,195 | CN22: 210760 | CO22: 165 | CP22: =BB55 -> 0 | CQ22: =BC55 -> 0 | CR22: =BD55 -> 0 | CS22: =BE55 -> 0 | CT22: =BF55 -> 0 | CU22: =BG55 -> 212127 | CV22: =BH55 -> 0 | CW22: =BI55 -> 213996 | ... DI22: =BU55 -> 212403
U23: NUMERO DE CAJAS | Z23: NUMERO DE CAJAS | AW23: SUXUN | AY23: NIPÓN | AZ23: STEEL FORCE | CI23: 211393 | CJ23: 207371 | CK23: LAMINA AGUILA LIGHT TIPO D 0.195 330 | CL23: 210655 | CM23: =VLOOKUP(CL23,$CI$2:$CK$20,3,0) -> LAMINA GEN LACADA SIZING TIPO D 0,195 | CN23: 0 | CO23: 0 | CP23: =BB54 -> 0 | CQ23: =BC54 -> 0 | CR23: =BD54 -> 0 | CS23: =BE54 -> 0 | CT23: =BF54 -> 0 | CU23: =BG54 -> 290 | CV23: =BH54 -> 0 | CW23: =BI54 -> 3060 | ... DI23: =BU54 -> 1692
U24: =+((V22*667)/11000) -> 614.00382 | Z24: =+((AA22*667)/11000) -> 393.95445 | AW24: CLUB | AY24: LACADA PARA POKER | AZ24: BASE BLANCA PONY | BY24: 725 | CG24: ALMACEN BT08 TINTAS | CI24: 211863 | CJ24: 211878 | CK24: LAMINA ÁGUILA LIGHT 330 PS TIPO D 0.195 | CL24: 210655 | CM24: =VLOOKUP(CL24,$CI$2:$CK$20,3,0) -> LAMINA GEN LACADA SIZING TIPO D 0,195 | CN24: 0 | CO24: 0
BY25: 212037 | CI25: 210761 | CJ25: 208472 | CK25: LAMINA POKER ROJA TIPO D 0.195 | CL25: 210654 | CM25: =VLOOKUP(CL25,$CI$2:$CK$20,3,0) -> LAMINA GEN LACADA TIPO D 0,195 | CN25: 0 | CO25: 0 | CP25: =AS55 -> 0 | CQ25: =AT55 -> 0 | CR25: =AU55 -> 207301 | CS25: =AV55 -> 212604
BJ26: =IFERROR(VLOOKUP(BJ25,$CI:$CM,3,0)," ") | BK26: =IFERROR(VLOOKUP(BK25,$CI:$CM,3,0)," ") | BL26: =IFERROR(VLOOKUP(BL25,$CI:$CM,3,0)," ") | BM26: =IFERROR(VLOOKUP(BM25,$CI:$CM,3,0)," ") | BN26: =IFERROR(VLOOKUP(BN25,$CI:$CM,3,0)," ") | BU26: =IFERROR(VLOOKUP(BU25,$CI:$CM,3,0)," ") | BV26: =IFERROR(VLOOKUP(BV25,$CI:$CM,3,0)," ") | BW26: =IFERROR(VLOOKUP(BW25,$CI:$CM,3,0)," ") | BX26: =IFERROR(VLOOKUP(BX25,$CI:$CM,3,0)," ") | BY26: =IFERROR(VLOOKUP(BY25,$CI:$CM,3,0)," ") -> BASE DORADA LACADA 0.195 | CI26: 211792 | CJ26: 211824 | CK26: LAMINA PILSEN QR TADA TIPO D 0.195 | CL26: 210654 | CM26: =VLOOKUP(CL26,$CI$2:$CK$20,3,0) -> LAMINA GEN LACADA TIPO D 0,195 | CN26: 0 | CO26: 0 | CP26: =AS54 -> 0 | CQ26: =AT54 -> 0 | CR26: =AU54 -> 7348 | CS26: =AV54 -> 2413
BY27: SUXUN | CI27: 212403 | CJ27: 212407 | CK27: LAMINA COSTEÑA BACANA 2000 TP D 0.195 | CL27: 210654 | CM27: =VLOOKUP(CL27,$CI$2:$CK$20,3,0) -> LAMINA GEN LACADA TIPO D 0,195 | CN27: 0 | CO27: 0
BY28: TEST CON AMARILLOS | CI28: 211691 | CJ28: 211311 | CK28: LAMINA NATIVA SUR TIPO D 0.195 | CL28: 210654 | CM28: =VLOOKUP(CL28,$CI$2:$CK$20,3,0) -> LAMINA GEN LACADA TIPO D 0,195 | CN28: 0 | CO28: 0 | CP28: =AS61 -> 206458 | CQ28: =AT61 -> 210760 | CR28: =AU61 -> 213637 | CS28: =AV61 -> 213367 | CT28: =AW61 -> 0 | CU28: =AX61 -> 0 | CV28: =AY61 -> 0 | CW28: =AZ61 -> 0 | ... DR28: =BU61 -> 0
CI29: 211672 | CJ29: 208078 | CK29: LAMINA COLA & POLA TIPO D 0.195 | CL29: 211671 | CM29: =VLOOKUP(CL29,$CI$2:$CK$20,3,0) -> LAMINA BASE AGUILA LACA TIPO D 0.195 | CN29: 0 | CO29: 0 | CP29: =AS60 -> 4693 | CQ29: =AT60 -> 4760 | CR29: =AU60 -> 1037 | CS29: =AV60 -> 520 | CT29: =AW60 -> 0 | CU29: =AX60 -> 0 | CV29: =AY60 -> 0 | CW29: =AZ60 -> 0 | ... DR29: =BU60 -> 0
CI30: 211305 | CJ30: 209630 | CK30: LAMINA YO ME CUIDO PERU TIPO D 0.195 | CL30: 210655 | CM30: =VLOOKUP(CL30,$CI$2:$CK$20,3,0) -> LAMINA GEN LACADA SIZING TIPO D 0,195 | CN30: 0 | CO30: 0
BT31: 218 | BU31: 452 | BV31: 1176 | BW31: 4207 | BX31: 6127 | BY31: =1400+1404+1878+1253+1880+1819-81 -> 9553 | CI31: 212127 | CJ31: 212195 | CK31: LAMINA YO ME CUIDO PERU ST TIPO D 0.195 | CL31: 210655 | CM31: =VLOOKUP(CL31,$CI$2:$CK$20,3,0) -> LAMINA GEN LACADA SIZING TIPO D 0,195 | CN31: 0 | CO31: 0
BT32: 211209 | BU32: 206454 | BV32: 206453 | BW32: 207544 | BX32: 206455 | BY32: 210654 | CI32: 212481 | CJ32: 209629 | CK32: LAMINA GOLDEN TIPO D 0.195 | CL32: 210655 | CM32: =VLOOKUP(CL32,$CI$2:$CK$20,3,0) -> LAMINA GEN LACADA SIZING TIPO D 0,195 | CN32: 0 | CO32: 0
BQ33: =IFERROR(VLOOKUP(BQ32,$CI:$CM,3,0)," ") | BR33: =IFERROR(VLOOKUP(BR32,$CI:$CM,3,0)," ") | BS33: =IFERROR(VLOOKUP(BS32,$CI:$CM,3,0)," ") | BT33: =IFERROR(VLOOKUP(BT32,$CI:$CM,3,0)," ") -> LAMINA CORONA MARTE TIPO D 0.195 | BU33: =IFERROR(VLOOKUP(BU32,$CI:$CM,3,0)," ") -> LAM BASE BLANCA LACADA TIPO D 0,17 | BV33: LAMINA LACADA TIPO D LG 0,17 | BW33: =IFERROR(VLOOKUP(BW32,$CI:$CM,3,0)," ") -> LAMINA LACADA TIPO A LG 0,17 | BX33: =IFERROR(VLOOKUP(BX32,$CI:$CM,3,0)," ") -> LAM GEN SIZING T/RENTE LACA TIPO D LG 0.17 | BY33: =IFERROR(VLOOKUP(BY32,$CI:$CM,3,0)," ") -> LAMINA GEN LACADA TIPO D 0,195 | CI33: 211306 | CJ33: 209631 | CK33: LAMINA CUSQUEÑA CALIDAD TIPO D 0.195 | CL33: 210655 | CM33: =VLOOKUP(CL33,$CI$2:$CK$20,3,0) -> LAMINA GEN LACADA SIZING TIPO D 0,195 | CN33: 0 | CO33: 0
BT34: STEEL FORCE | BU34: STEEL FORCE | BV34: RASSELSTEIN | BW34: NIPÓN | BX34: RASSELSTEIN | BY34: JINTAI | CI34: 212066 | CJ34: 212013 | CK34: LAMINA CC ROJA TIPO D 0.195 NEW VBI | CL34: 212037 | CM34: =VLOOKUP(CL34,$CI$2:$CK$20,3,0) -> BASE DORADA LACADA 0.195 | CN34: 0 | CO34: 0
BT35: LACA + BASE BLANCA RASELSTEIN | BU35: LACA + BASE BLANCA RASELSTEIN | BV35: LACA 0.17 | BW35: LACADA + SIZING | BX35: 0.17 LACADA +SIZING | BY35: OXIDADA | CI35: 212068 | CJ35: 212014 | CK35: LAMINA CC NEGRA TIPO D 0.195 NEW VBI | CL35: 212037 | CM35: =VLOOKUP(CL35,$CI$2:$CK$20,3,0) -> BASE DORADA LACADA 0.195 | CN35: 0 | CO35: 0
CI36: 212019 | CJ36: 212016 | CK36: LAMINA TIPO D 0.195 CLUB COLOM NEW VBI | CL36: 212037 | CM36: =VLOOKUP(CL36,$CI$2:$CK$20,3,0) -> BASE DORADA LACADA 0.195 | CN36: 0 | CO36: 0 | CQ36: CODIGO | CR36: REFERENCIA | CV36: 1 | CW36: 2 | CX36: 3 | CY36: 4 | CZ36: 5 | DA36: 6 | DB36: 7 | DC36: 8 | DD36: 9 | DE36: 10 | DF36: 11 | DG36: 12 | DH36: 13 | DI36: FISICO | DJ36: SAP | DK36: BLO
CB37: PNC LAMINA | CI37: 212378 | CJ37: 212265 | CK37: LAMINA CC OKTOBERFEST TIPOD 0.195 | CL37: 210655 | CM37: =VLOOKUP(CL37,$CI$2:$CK$20,3,0) -> LAMINA GEN LACADA SIZING TIPO D 0,195 | CN37: 0 | CO37: 0 | CQ37: 213679 | CR37: =VLOOKUP(CQ37,$CI$4:$CK$167,3,0) -> LAMINA CLUB ESMERALDA PROMOCION 0.195 | DI37: =SUM(CV37:DH37) -> 0 | DK37: =+DJ37-DI37 -> 0
CI38: 211217 | CJ38: 212080 | CK38: LAMINA BUDWEISER TW TIPO D 0.195 | CL38: 211747 | CM38: =VLOOKUP(CL38,$CI$2:$CK$20,3,0) -> LAM SIZING ALUM LACA OXY TIPO D 0.195 | CN38: 0 | CO38: 0 | CQ38: 213637 | CR38: =VLOOKUP(CQ38,$CI$4:$CK$167,3,0) -> LAMINA AGUILA LGT PROMO ALFA TIP D 0.195 | DI38: =SUM(CV38:DH38) -> 0 | DK38: =+DJ38-DI38 -> 0
B39: 1 | C39: 3 | D39: 2 | E39: 3 | F39: 3 | G39: 4 | H39: 5 | I39: 5 | CI39: 211216 | CJ39: 208453 | CK39: LAMINA PONY ROJA CI TIPO D 0.195 | CL39: 210654 | CM39: =VLOOKUP(CL39,$CI$2:$CK$20,3,0) -> LAMINA GEN LACADA TIPO D 0,195 | CN39: 0 | CO39: 0 | CQ39: 213738 | CR39: =VLOOKUP(CQ39,$CI$4:$CK$167,3,0) -> LAMINA POKER RENOVACION | CV39: 360 | CW39: 1301 | CX39: 940 | CY39: 451 | CZ39: 1918 | DA39: 1490 | DI39: =SUM(CV39:DH39) -> 6460 | DK39: =+DJ39-DI39 -> -6460
CG40: OFICINA ASL, SLI | CI40: 212315 | CJ40: 202732 | CK40: LAMINA COSTEÑITA CBARRAS LG TIPOD.0.195 | CL40: 210655 | CM40: =VLOOKUP(CL40,$CI$2:$CK$20,3,0) -> LAMINA GEN LACADA SIZING TIPO D 0,195 | CN40: 0 | CO40: 0 | CQ40: 211306 | CR40: =VLOOKUP(CQ40,$CI$4:$CK$167,3,0) -> LAMINA CUSQUEÑA CALIDAD TIPO D 0.195 | CV40: 280 | CW40: 1252 | DI40: =SUM(CV40:DH40) -> 1532 | DK40: =+DJ40-DI40 -> -1532
CI41: 212604 | CJ41: 212601 | CK41: LAMINA COSTEÑA ROJA TIPO D0.195 | CL41: 210654 | CM41: =VLOOKUP(CL41,$CI$2:$CK$20,3,0) -> LAMINA GEN LACADA TIPO D 0,195 | CN41: 0 | CO41: 0 | CQ41: 212403 | CR41: =VLOOKUP(CQ41,$CI$4:$CK$167,3,0) -> LAMINA COSTEÑA BACANA 2000 TP D 0.195 | CV41: 1367 | CW41: 1260 | DI41: =SUM(CV41:DH41) -> 2627 | DK41: =+DJ41-DI41 -> -2627
CI42: 211209 | CJ42: 208479 | CK42: LAMINA CORONA MARTE TIPO D 0.195 | CL42: 211749 | CM42: =VLOOKUP(CL42,$CI$2:$CK$20,3,0) -> LAM BASE BLANCA LACA OXY TIPO 0.195 | CN42: 0 | CO42: 0 | CQ42: 210654 | CR42: =VLOOKUP(CQ42,$CI$4:$CK$167,3,0) -> LAMINA GEN LACADA TIPO D 0,195 | CV42: 1500 | CW42: 850 | CX42: 350 | DI42: =SUM(CV42:DH42) -> 2700 | DK42: =+DJ42-DI42 -> -2700
CI43: 212321 | CJ43: 206051 | CK43: LAMINA BBC LG TIPOD.0.195 | CL43: 212357 | CM43: =VLOOKUP(CL43,$CI$2:$CK$20,3,0) -> LAMINA LACADA BBC LG TIPO D0.195 | CN43: 0 | CO43: 0 | CQ43: 213677 | CR43: =VLOOKUP(CQ43,$CI$4:$CK$167,3,0) -> LAMINA LACADA SIZING PROM TIPO D 0.195 | CV43: 700 | CW43: 286 | CX43: 475 | DI43: =SUM(CV43:DH43) -> 1461 | DK43: =+DJ43-DI43 -> -1461
BJ44: 78-73-76 | CI44: 212751 | CJ44: 212738 | CK44: LAMINA AGUILA ORIGINAL NV TIPO D0.195 | CL44: 210655 | CM44: =VLOOKUP(CL44,$CI$2:$CK$20,3,0) -> LAMINA GEN LACADA SIZING TIPO D 0,195 | CN44: 0 | CO44: 0 | CQ44: 213732 | CR44: =VLOOKUP(CQ44,$CI$4:$CK$167,3,0) -> LAMINA COSTEÑA BACANA CENTRO TIPO D 0.195 | DI44: =SUM(CV44:DH44) -> 0 | DK44: =+DJ44-DI44 -> 0
B45: 5 | C45: 5 | D45: 5 | E45: 5 | AF45: 2 | AH45: 4 | AI45: 4 | AJ45: 4 | AL45: 5 | AM45: 5 | AN45: 5 | AO45: 5 | AP45: 5 | AQ45: 5 | CI45: 212797 | CJ45: 212814 | CK45: LAMINA CORONA OLIMPICOS TIPO D 0.195 | CL45: 211749 | CM45: =VLOOKUP(CL45,$CI$2:$CK$20,3,0) -> LAM BASE BLANCA LACA OXY TIPO 0.195 | CN45: {=TRANSPOSE(CP4:DN4)} -> 0 | CO45: {=TRANSPOSE(CP5:DN5)} -> 0 | CQ45: 211749 | CR45: =VLOOKUP(CQ45,$CI$1:$CK$167,3,0) -> LAM BASE BLANCA LACA OXY TIPO 0.195 | CV45: 2270 | DI45: =SUM(CV45:DH45) -> 2270 | DK45: =+DJ45-DI45 -> -2270
B46: 5 | C46: 5 | D46: 5 | E46: 5 | AH46: 5 | AI46: 5 | AJ46: 5 | AL46: 5 | AM46: 5 | AN46: 5 | AO46: 5 | AP46: 5 | AQ46: 5 | AS46: 20 | AT46: 19 | AU46: 18 | AV46: 17 | AX46: M-M | BC46: 16 | BD46: 15 | BE46: 14 | BG46: 16 | BH46: 15 | BI46: 14 | BJ46: 13 | BK46: 12 | BL46: 11 | BM46: 10 | BP46: 6 | BQ46: 5 | BR46: 4 | BS46: 3 | BT46: 2 | BU46: 1 | CI46: 212749 | CJ46: 212739 | CK46: LAMINA AGUILA LIGHT NV TIPO D0.195 | CL46: 210655 | CM46: =VLOOKUP(CL46,$CI$2:$CK$20,3,0) -> LAMINA GEN LACADA SIZING TIPO D 0,195 | CN46: 0 | CO46: 0 | CQ46: 212315 | CR46: =VLOOKUP(CQ46,$CI$4:$CK$167,3,0) -> LAMINA COSTEÑITA CBARRAS LG TIPOD.0.195 | CV46: 1149 | CW46: 46 | CX46: 52 | DI46: =SUM(CV46:DH46) -> 1247 | DK46: =+DJ46-DI46 -> -1247
AE47: 3 | AF47: 5 | AH47: 5 | AI47: 5 | AJ47: 5 | AL47: 5 | AM47: 5 | AN47: 5 | AO47: 5 | AP47: 5 | AQ47: 5 | AU47: 7348 | AV47: =1211+1202 -> 2413 | AX47: 206890 | AY47: =IFERROR(VLOOKUP(AX47,$CI:$CM,3,0)," ") -> LAMINA PONY MALTA TW | AZ47: 1692 | BA47: 2 | BG47: 290 | BI47: =1557+1503 -> 3060 | BJ47: =1630+1590 -> 3220 | BL47: =1539+1485+1550 -> 4574 | BR47: 1629 | BS47: =1665+1685+1657 -> 5007 | BU47: 1692 | BV47: DEFECTOS | BW47: 210655 | BX47: =IFERROR(VLOOKUP(BW47,$CI:$CM,3,0)," ") -> LAMINA GEN LACADA SIZING TIPO D 0,195 | BY47: 1700 | BZ47: =SUM(BY47:BY47) -> 1700 | CI47: 212694 | CJ47: 212703 | CK47: LAMINA CLUB COLOMBIA TRIGO TIPO D0.195 | CL47: 212037 | CM47: =VLOOKUP(CL47,$CI$2:$CK$20,3,0) -> BASE DORADA LACADA 0.195 | CN47: 0 | CO47: 0 | CQ47: 212127 | CR47: =VLOOKUP(CQ47,$CI$4:$CK$167,3,0) -> LAMINA YO ME CUIDO PERU ST TIPO D 0.195 | CV47: 1400 | CW47: 1135 | CX47: 540 | CY47: 348 | CZ47: 1400 | DI47: =SUM(CV47:DH47) -> 4823 | DK47: =+DJ47-DI47 -> -4823
AE48: 3 | AF48: 5 | AH48: 5 | AI48: 5 | AJ48: 5 | AL48: 5 | AM48: 5 | AN48: 5 | AO48: 5 | AP48: 4 | AQ48: 2 | AX48: 210128 | AY48: =IFERROR(VLOOKUP(AX48,$CI:$CM,3,0)," ") -> LAMINA POKER BBC PURAMALTA TIPO D 0.17 | AZ48: 1630 | BA48: 1 | BJ48: 1690 | BL48: =1550+1547+1500 -> 4597 | BM48: 1608 | BQ48: =1691-857 -> 834 | BS48: =1680+1607+1551 -> 4838 | BV48: DEFECTOS | BW48: 212403 | BX48: =IFERROR(VLOOKUP(BW48,$CI:$CM,3,0)," ") -> LAMINA COSTEÑA BACANA 2000 TP D 0.195 | BY48: =163+150 -> 313 | BZ48: =SUM(BY48:BY48) -> 313 | CI48: 212917 | CJ48: 212916 | CK48: LAMINA AGUILA COPA AMERICA TIPO D0.195 | CL48: 211671 | CM48: =VLOOKUP(CL48,$CI$2:$CK$20,3,0) -> LAMINA BASE AGUILA LACA TIPO D 0.195 | CN48: 0 | CO48: 0 | CQ48: 211208 | CR48: =VLOOKUP(CQ48,$CI$4:$CK$167,3,0) -> LAMINA PILSEN GENERICA TIP D 0.195 | DI48: =SUM(CV48:DH48) -> 0 | DK48: =+DJ48-DI48 -> 0
AA49: 2 | AB49: 5 | AC49: 5 | AD49: 5 | AE49: 5 | AF49: 5 | AH49: 5 | AI49: 5 | AJ49: 5 | AL49: 5 | AM49: 5 | AN49: 5 | AO49: 5 | AP49: 4 | AQ49: 0 | AX49: 209962 | AY49: =IFERROR(VLOOKUP(AX49,$CI:$CM,3,0)," ") -> LAMINA PACIFICO PERU | AZ49: 500 | BA49: 5 | BJ49: =1681+1669 -> 3350 | BL49: =1586+1573+1540 -> 4699 | BM49: =740-98 -> 642 | BQ49: 340 | BS49: =1768+1669+1660 -> 5097 | BV49: DEFECTOS | BW49: 212127 | BX49: =IFERROR(VLOOKUP(BW49,$CI:$CM,3,0)," ") -> LAMINA YO ME CUIDO PERU ST TIPO D 0.195 | BY49: =120+767 -> 887 | BZ49: =SUM(BY49:BY49) -> 887 | CI49: 213210 | CJ49: 213208 | CK49: LAMINA UV TOUR AGUILA TIPO D0.195 | CL49: 210655 | CM49: =VLOOKUP(CL49,$CI$2:$CK$20,3,0) -> LAMINA GEN LACADA SIZING TIPO D 0,195 | CN49: 0 | CO49: 0 | CQ49: 211209 | CR49: =VLOOKUP(CQ49,$CI$4:$CK$167,3,0) -> LAMINA CORONA MARTE TIPO D 0.195 | CV49: 352 | CW49: 1606 | CX49: 475 | DI49: =SUM(CV49:DH49) -> 2433 | DK49: =+DJ49-DI49 -> -2433
AA50: 3 | AB50: 5 | AC50: 5 | AD50: 5 | AE50: 5 | AF50: 5 | AH50: 5 | AI50: 5 | AJ50: 5 | AL50: 5 | AM50: 5 | AN50: 5 | AO50: 5 | AP50: 4 | AQ50: 0 | AX50: 204388 | AY50: =IFERROR(VLOOKUP(AX50,$CI:$CM,3,0)," ") -> LAMINA REDDS TIPO D LG FASE II | AZ50: 43 | BA50: 10 | BJ50: 1690 | BL50: 1453 | BM50: 556 | BS50: 1640 | BV50: DEFECTOS | BW50: 212127 | BX50: =IFERROR(VLOOKUP(BW50,$CI:$CM,3,0)," ") -> LAMINA YO ME CUIDO PERU ST TIPO D 0.195 | BY50: 1216 | BZ50: =SUM(BY50:BY50) -> 1216 | CI50: 213209 | CJ50: 213208 | CK50: LAMINA COV TOUR AGUILA TIPO D0.195 | CL50: 210654 | CM50: =VLOOKUP(CL50,$CI$2:$CK$20,3,0) -> LAMINA GEN LACADA TIPO D 0,195 | CN50: 0 | CO50: 0 | CQ50: 210655 | CR50: =VLOOKUP(CQ50,$CI$4:$CK$167,3,0) -> LAMINA GEN LACADA SIZING TIPO D 0,195 | CV50: 1680 | CW50: 400 | DI50: =SUM(CV50:DH50) -> 2080 | DK50: =+DJ50-DI50 -> -2080
C51: 4 | D51: 4 | E51: 4 | F51: 4 | G51: 4 | H51: 4 | I51: 4 | K51: 4 | L51: 4 | M51: 4 | N51: 4 | O51: 4 | P51: 4 | Q51: 4 | R51: 4 | AC51: 4 | AD51: 4 | AE51: 4 | AF51: 3 | AH51: 2 | AI51: 3 | AJ51: 3 | AL51: 5 | AM51: 5 | AN51: 5 | AO51: 5 | AP51: 5 | AQ51: 0 | AX51: 202737 | AY51: =IFERROR(VLOOKUP(AX51,$CI:$CM,3,0)," ") -> LAMINA POKER 330/750R TIPO A LG | AZ51: 2854 | BA51: 7 | BJ51: =1689+1636 -> 3325 | BM51: 1198 | BN51: 2 saldos uno grande uno 200 ñam | BV51: DEFECTOS | BW51: 213637 | BX51: =IFERROR(VLOOKUP(BW51,$CI:$CM,3,0)," ") -> LAMINA AGUILA LGT PROMO ALFA TIP D 0.195 | BY51: 733 | BZ51: =SUM(BY51:BY51) -> 733 | CI51: 213147 | CJ51: 213146 | CK51: LAMINA AGUILA IMPERIAL TIPO D0.195 | CL51: 210656 | CM51: =VLOOKUP(CL51,$CI$2:$CK$20,3,0) -> LAMINA GEN BASE BLANCA LACADA TIPO D 0.195 | CN51: 0 | CO51: 0 | CQ51: 210761 | CR51: =VLOOKUP(CQ51,$CI$4:$CK$167,3,0) -> LAMINA POKER ROJA TIPO D 0.195 | DI51: =SUM(CV51:DH51) -> 0 | DK51: =+DJ51-DI51 -> 0
Z52: 2 | AL52: 5 | AM52: 5 | AN52: 5 | AO52: 0 | AP52: 0 | AQ52: 0 | AX52: 210761 | AY52: =IFERROR(VLOOKUP(AX52,$CI:$CM,3,0)," ") -> LAMINA POKER ROJA TIPO D 0.195 | AZ52: 886 | BA52: 4 | BJ52: 900 | BV52: DEFECTOS | BW52: 210655 | BX52: =IFERROR(VLOOKUP(BW52,$CI:$CM,3,0)," ") -> LAMINA GEN LACADA SIZING TIPO D 0,195 | BY52: 540 | BZ52: =SUM(BY52:BY52) -> 540 | CI52: 212787 | CJ52: 212812 | CK52: LAMINA CORONA CERO TIPO D 0,195 | CL52: 211749 | CM52: =VLOOKUP(CL52,$CI$2:$CK$20,3,0) -> LAM BASE BLANCA LACA OXY TIPO 0.195 | CN52: 0 | CO52: 0 | CQ52: 213246 | CR52: =VLOOKUP(CQ52,$CI$4:$CK$167,3,0) -> LAMINA CLUB PREMIUM CLASICA TIPO D 0.195 | DI52: =SUM(CV52:DH52) -> 0 | DK52: =+DJ52-DI52 -> 0
AX53: 213364 | AY53: =IFERROR(VLOOKUP(AX53,$CI:$CM,3,0)," ") -> LAMINA PILSENER ECUADOR TW TIPO D 0.195 | AZ53: 1404 | BA53: 3 | BJ53: 1605 | BV53: DEFECTOS | BW53: 213637 | BX53: =IFERROR(VLOOKUP(BW53,$CI:$CM,3,0)," ") -> LAMINA AGUILA LGT PROMO ALFA TIP D 0.195 | BY53: =1605-424 -> 1181 | BZ53: =SUM(BY53:BY53) -> 1181 | CI53: 213237 | CJ53: 213229 | CK53: LAMINA COSTEÑA LA VIDA BACANA | CL53: 210654 | CM53: =VLOOKUP(CL53,$CI$2:$CK$20,3,0) -> LAMINA GEN LACADA TIPO D 0,195 | CN53: 0 | CO53: 0 | CQ53: 213239 | CR53: =VLOOKUP(CQ53,$CI$4:$CK$167,3,0) -> LAMINA PILSENER TIPO D 0.195 | DI53: =SUM(CV53:DH53) -> 0 | DK53: =+DJ53-DI53 -> 0
B54: =+SUM(C11:C18)+SUM(Y52:AJ53)+SUM(I13:P13)+SUM(B38:I39)+SUM(B47:V48)+SUM(Z49:AJ50) -> 141 | C54: STEEL FORCE | D54: =+SUM(B45:V46)+SUM(Y45:AJ48)+SUM(B11:B15)+SUM(B38:I38)+SUM(B49:X50)+SUM(Y52) -> 126 | E54: SUXUN | F54: =SUM(B35:I37)+SUM(D11:D17) -> 0 | G54: JINTAI D 0,195 | H54: =+SUM(C51:I51)+SUM(K51:Q51)+SUM(Z51:AF51)+SUM(AL45:AQ52) -> 275 | I54: TIPO A | J54: =+SUM(AH51:AJ51) -> 8 | K54: JINTAI D 0,17 | M54: SUXUN 1500 | O54: RASELSTEIN 0.17 | AS54: =SUM(AS47:AS53) -> 0 | AT54: =SUM(AT47:AT53) -> 0 | AU54: =SUM(AU47:AU53) -> 7348 | AV54: =SUM(AV47:AV53) -> 2413 | AX54: 213246 | AY54: =IFERROR(VLOOKUP(AX54,$CI:$CM,3,0)," ") -> LAMINA CLUB PREMIUM CLASICA TIPO D 0.195 | AZ54: 1468 | BA54: 9 | BC54: =SUM(BC47:BC53) -> 0 | BD54: =SUM(BD47:BD53) -> 0 | BE54: =SUM(BE47:BE53) -> 0 | BG54: =SUM(BG47:BG53) -> 290 | BH54: =SUM(BH47:BH53) -> 0 | BI54: =SUM(BI47:BI53) -> 3060 | BJ54: =SUM(BJ47:BJ53) -> 15780 | BK54: =SUM(BK47:BK53) -> 0 | BL54: =SUM(BL47:BL53) -> 15323 | BM54: =SUM(BM47:BM53) -> 4004 | BP54: =SUM(BP47:BP53) -> 0 | BQ54: =SUM(BQ47:BQ53) -> 1174 | BR54: =SUM(BR47:BR53) -> 1629 | BS54: =SUM(BS47:BS53) -> 16582 | BT54: =SUM(BT47:BT53) -> 0 | BU54: =SUM(BU47:BU53) -> 1692 | BV54: DEFECTOS | BW54: 213637 | BX54: =IFERROR(VLOOKUP(BW54,$CI:$CM,3,0)," ") -> LAMINA AGUILA LGT PROMO ALFA TIP D 0.195 | BY54: =1670-980 -> 690 | BZ54: =SUM(BY54:BY54) -> 690 | CG54: MOLIDO DE PVC | CI54: 213356 | CJ54: 213340 | CK54: LAMINA AGUILA CARIBE | CL54: 210655 | CM54: =VLOOKUP(CL54,$CI$2:$CK$20,3,0) -> LAMINA GEN LACADA SIZING TIPO D 0,195 | CN54: 0 | CO54: 0 | CQ54: 211691 | CR54: =VLOOKUP(CQ54,$CI$4:$CK$167,3,0) -> LAMINA NATIVA SUR TIPO D 0.195 | DI54: =SUM(CV54:DH54) -> 0 | DK54: =+DJ54-DI54 -> 0
AU55: 207301 | AV55: 212604 | AX55: 211217 | AY55: =IFERROR(VLOOKUP(AX55,$CI:$CM,3,0)," ") -> LAMINA BUDWEISER TW TIPO D 0.195 | AZ55: 1728 | BA55: 14 | BG55: 212127 | BI55: 213996 | BJ55: 213637 | BL55: 211208 | BM55: 213738 | BQ55: 211209 | BR55: 212787 | BS55: 212315 | BU55: 212403 | BV55: DEFECTOS | BW55: 213738 | BX55: =IFERROR(VLOOKUP(BW55,$CI:$CM,3,0)," ") -> LAMINA POKER RENOVACION | BY55: 1460 | BZ55: =SUM(BY55:BY55) -> 1460 | CI55: 213343 | CJ55: 213340 | CK55: LAMINA AGUILA EL CARIBE D 0.195 | CL55: 210655 | CM55: =VLOOKUP(CL55,$CI$2:$CK$20,3,0) -> LAMINA GEN LACADA SIZING TIPO D 0,195 | CN55: 0 | CO55: 0 | CQ55: 210760 | CR55: =VLOOKUP(CQ55,$CI$4:$CK$167,3,0) -> LAMINA AGUILA AZUL TIPO D 0.195 | CV55: 486 | CW55: 280 | CX55: 300 | CY55: 840 | DI55: =SUM(CV55:DH55) -> 1906 | DK55: =+DJ55-DI55 -> -1906
AS56: =IFERROR(VLOOKUP(AS55,$CI:$CM,3,0)," ") | AT56: =IFERROR(VLOOKUP(AT55,$CI:$CM,3,0)," ") | AU56: =IFERROR(VLOOKUP(AU55,$CI:$CM,3,0)," ") -> LAMINA COSTEÑITA TIPO D | AV56: =IFERROR(VLOOKUP(AV55,$CI:$CM,3,0)," ") -> LAMINA COSTEÑA ROJA TIPO D0.195 | AX56: 208477 | AY56: =IFERROR(VLOOKUP(AX56,$CI:$CM,3,0)," ") -> LAMINA POKER ROJA RET LG TIPO D 0,17 | AZ56: 1977 | BA56: 8 | BC56: =IFERROR(VLOOKUP(BC55,$CI:$CM,3,0)," ") | BD56: =IFERROR(VLOOKUP(BD55,$CI:$CM,3,0)," ") | BE56: =IFERROR(VLOOKUP(BE55,$CI:$CM,3,0)," ") | BG56: =IFERROR(VLOOKUP(BG55,$CI:$CM,3,0)," ") -> LAMINA YO ME CUIDO PERU ST TIPO D 0.195 | BH56: =IFERROR(VLOOKUP(BH55,$CI:$CM,3,0)," ") | BI56: =IFERROR(VLOOKUP(BI55,$CI:$CM,3,0)," ") -> LAMINA AGUILA MF 2026 UV TIPO D 0,195 | BJ56: =IFERROR(VLOOKUP(BJ55,$CI:$CM,3,0)," ") -> LAMINA AGUILA LGT PROMO ALFA TIP D 0.195 | BK56: =IFERROR(VLOOKUP(BK55,$CI:$CM,3,0)," ") | BL56: =IFERROR(VLOOKUP(BL55,$CI:$CM,3,0)," ") -> LAMINA PILSEN GENERICA TIP D 0.195 | BM56: =IFERROR(VLOOKUP(BM55,$CI:$CM,3,0)," ") -> LAMINA POKER RENOVACION | BP56: =IFERROR(VLOOKUP(BP55,$CI:$CM,3,0)," ") | BQ56: =IFERROR(VLOOKUP(BQ55,$CI:$CM,3,0)," ") -> LAMINA CORONA MARTE TIPO D 0.195 | BR56: =IFERROR(VLOOKUP(BR55,$CI:$CM,3,0)," ") -> LAMINA CORONA CERO TIPO D 0,195 | BS56: =IFERROR(VLOOKUP(BS55,$CI:$CM,3,0)," ") -> LAMINA COSTEÑITA CBARRAS LG TIPOD.0.195 | BT56: =IFERROR(VLOOKUP(BT55,$CI:$CM,3,0)," ") | BU56: =IFERROR(VLOOKUP(BU55,$CI:$CM,3,0)," ") -> LAMINA COSTEÑA BACANA 2000 TP D 0.195 | CI56: 213354 | CJ56: 213328 | CK56: LAMINA REDDS CITRUS UV 0.195 | CL56: 210656 | CM56: =VLOOKUP(CL56,$CI$2:$CK$20,3,0) -> LAMINA GEN BASE BLANCA LACADA TIPO D 0.195 | CN56: 0 | CO56: 0 | CQ56: 213868 | CR56: =VLOOKUP(CQ56,$CI$4:$CK$167,3,0) -> LAMINA TAPA TEST CONV TIPO D0.195 | CV56: 999 | CW56: 878 | CX56: 26 | DI56: =SUM(CV56:DH56) -> 1903 | DK56: =+DJ56-DI56 -> -1903
B57: PROVEEDOR | D57: UNIDADES | E57: PESO | F57: KILOGRAMOS | H57: LAMINA VIRGEN TIPO D | M57: LAMINA EN PROCESO | R57: LAMINA TERMINADA | W57: TOTAL CAPACIDAD FABRICA | AU57: N/A | AV57: JINTAI | AX57: 212019 | AY57: =IFERROR(VLOOKUP(AX57,$CI:$CM,3,0)," ") -> LAMINA TIPO D 0.195 CLUB COLOM NEW VBI | AZ57: 1349 | BA57: 11 | BG57: STEEL FORCE | BI57: STEEL FORCE | BJ57: SUXUN | BL57: STEEL FORCE | BM57: SUXUN | BQ57: SUXUN | BR57: SUXUN | BS57: SUXUN | BU57: SUXUN | CI57: 213415 | CJ57: 213413 | CK57: LAMINA AGUILA GOLES UV TIPO D0.195 | CL57: 211671 | CM57: =VLOOKUP(CL57,$CI$2:$CK$20,3,0) -> LAMINA BASE AGUILA LACA TIPO D 0.195 | CN57: 0 | CO57: 0 | CQ57: 213802 | CR57: =VLOOKUP(CQ57,$CI$4:$CK$167,3,0) -> LAMINA MCHELOB ULTRA NRB 330 TIPO D0.195 | CV57: 187 | DI57: =SUM(CV57:DH57) -> 187 | DK57: =+DJ57-DI57 -> -187
B58: STEEL FORCE | D58: =B54*1548 -> 218268 | E58: 1.291 | F58: =D58*E58 -> 281783.99 | AT58: 13 | AX58: 213352 | AY58: =IFERROR(VLOOKUP(AX58,$CI:$CM,3,0)," ") -> LAMINA NUTRI MALTA D 0.195 | AZ58: 1519 | BA58: 6 | CI58: 213246 | CJ58: 213304 | CK58: LAMINA CLUB PREMIUM CLASICA TIPO D 0.195 | CL58: 210655 | CM58: =VLOOKUP(CL58,$CI$2:$CK$20,3,0) -> LAMINA GEN LACADA SIZING TIPO D 0,195 | CN58: 0 | CO58: 0 | CQ58: 213885 | CR58: =VLOOKUP(CQ58,$CI$4:$CK$167,3,0) -> LAMINA TIPO D PILSENER MUNDIAL ECUADOR | CV58: 139 | DI58: =SUM(CV58:DH58) -> 139 | DK58: =+DJ58-DI58 -> -139
B59: TIPO A | D59: =H54*1690 -> 464750 | E59: 1.014 | F59: =D59*E59 -> 471256.5 | H59: CAPACIDAD | J59: INVENTARIO | M59: CAPACIDAD | O59: INVENTARIO | R59: CAPACIDAD | T59: INVENTARIO | W59: CAPACIDAD: | Y59: INVENTARIO | AS59: 23 | AT59: 21 | AU59: 20 | AV59: 19 | AX59: 213343 | AY59: =IFERROR(VLOOKUP(AX59,$CI:$CM,3,0)," ") -> LAMINA AGUILA EL CARIBE D 0.195 | AZ59: 629 | BA59: 15 | BC59: 17 | BD59: 16 | BE59: 15 | BG59: 14 | BH59: 13 | BI59: 12 | BJ59: 11 | BK59: 10 | BL59: 9 | BM59: 8 | BP59: 6 | BQ59: 5 | BR59: 4 | BS59: 3 | BT59: 2 | BU59: 1 | BZ59: N/A | CI59: 213438 | CJ59: 213420 | CK59: LAMINA COLA & POLA UV TIPO D0.195 | CL59: 211671 | CM59: =VLOOKUP(CL59,$CI$2:$CK$20,3,0) -> LAMINA BASE AGUILA LACA TIPO D 0.195 | CN59: 212037 | CO59: 480 | CQ59: 213367 | CR59: =VLOOKUP(CQ59,$CI$4:$CK$167,3,0) -> LAMINA CLUB PREMIUM TW ECUADOR D0.195 | DI59: =SUM(CV59:DH59) -> 0 | DK59: =+DJ59-DI59 -> 0
B60: SUXUN | D60: =(L54*1500)+(D54*1680) -> 211680 | E60: 1.292 | F60: =D60*E60 -> 273490.56 | H60: =1170*1500 -> 1755000 | J60: =+J61*1500 -> 441148 | M60: =330*1600 -> 528000 | O60: =+SUM(AI10:BC13)+SUM(BJ10:BN17)+SUM(BU10:BY17)+SUM(BE10:BG13)+SUM(BQ31:BY31)+SUM(BU24:BY24)+SUM(AI20:BG20)+SUM(BJ24:BN24) -> 73242 | R60: =560*1600 -> 896000 | T60: =SUM(AS47:AV53)+SUM(BB47:BE53)+SUM(BF63:BI69)+SUM(BG47:BM53)+SUM(BO47:BU53)+SUM(BZ47:BZ55)+SUM(AS60:BU60) -> 90912 | W60: =SUM(H60+M60+R60) -> 3179000 | Y60: =SUM(J60+O60+T60) -> 605302 | AS60: 4693 | AT60: 4760 | AU60: =262+775 -> 1037 | AV60: 520 | BG60: =990+452+445 -> 1887 | BZ60: TROQUELADORA | CI60: 213352 | CJ60: 213341 | CK60: LAMINA NUTRI MALTA D 0.195 | CL60: 210656 | CM60: =VLOOKUP(CL60,$CI$2:$CK$20,3,0) -> LAMINA GEN BASE BLANCA LACADA TIPO D 0.195 | CN60: 0 | CO60: 0 | DI60: =SUM(DI37:DI59) -> 31768 | DJ60: =SUM(DJ37:DJ59) -> 0
B61: JINTAI 0,195 | D61: =(F54*1400) -> 0 | E61: 1.291 | F61: =D61*E61 -> 0 | H61: =H60/1500 -> 1170 | J61: =+D66/1500 -> 294.09867 | M61: =M60/1600 -> 330 | O61: =O60/1600 -> 45.77625 | R61: =R60/1600 -> 560 | T61: =T60/1600 -> 56.82 | W61: =W60/1600 -> 1986.875 | Y61: =Y60/1600 -> 378.31375 | AS61: 206458 | AT61: 210760 | AU61: 213637 | AV61: 213367 | BG61: 211209 | CI61: 213324 | CJ61: 213321 | CK61: LAMINA PONY MALTA GO 0.195 | CL61: 210656 | CM61: =VLOOKUP(CL61,$CI$2:$CK$20,3,0) -> LAMINA GEN BASE BLANCA LACADA TIPO D 0.195 | CN61: 207544 | CO61: 1690
B62: JINTAI 0.17 | D62: =J54*1400 -> 11200 | E62: 1.126 | F62: =D62*E62 -> 12611.2 | H62: =J60/H60 -> 0.25136638 | M62: =O60/M60 -> 0.13871591 | R62: =T60/R60 -> 0.10146429 | W62: =Y60/W60 -> 0.19040642 | AS62: =IFERROR(VLOOKUP(AS61,$CI:$CM,3,0)," ") -> LAMINA CLUB PREMIUM RET TIPO D 0,17 ECU | AT62: =IFERROR(VLOOKUP(AT61,$CI:$CM,3,0)," ") -> LAMINA AGUILA AZUL TIPO D 0.195 | AU62: =IFERROR(VLOOKUP(AU61,$CI:$CM,3,0)," ") -> LAMINA AGUILA LGT PROMO ALFA TIP D 0.195 | AV62: =IFERROR(VLOOKUP(AV61,$CI:$CM,3,0)," ") -> LAMINA CLUB PREMIUM TW ECUADOR D0.195 | BC62: =IFERROR(VLOOKUP(BC61,$CI:$CM,3,0)," ") | BD62: =IFERROR(VLOOKUP(BD61,$CI:$CM,3,0)," ") | BE62: =IFERROR(VLOOKUP(BE61,$CI:$CM,3,0)," ") | BG62: =IFERROR(VLOOKUP(BG61,$CI:$CM,3,0)," ") -> LAMINA CORONA MARTE TIPO D 0.195 | BH62: =IFERROR(VLOOKUP(BH61,$CI:$CM,3,0)," ") | BI62: =IFERROR(VLOOKUP(BI61,$CI:$CM,3,0)," ") | BJ62: =IFERROR(VLOOKUP(BJ61,$CI:$CM,3,0)," ") | BK62: =IFERROR(VLOOKUP(BK61,$CI:$CM,3,0)," ") | BL62: =IFERROR(VLOOKUP(BL61,$CI:$CM,3,0)," ") | BM62: =IFERROR(VLOOKUP(BM61,$CI:$CM,3,0)," ") | BP62: =IFERROR(VLOOKUP(BP61,$CI:$CM,3,0)," ") | BQ62: =IFERROR(VLOOKUP(BQ61,$CI:$CM,3,0)," ") | BR62: =IFERROR(VLOOKUP(BR61,$CI:$CM,3,0)," ") | BS62: =IFERROR(VLOOKUP(BS61,$CI:$CM,3,0)," ") | BT62: =IFERROR(VLOOKUP(BT61,$CI:$CM,3,0)," ") | BU62: =IFERROR(VLOOKUP(BU61,$CI:$CM,3,0)," ") | CI62: 213482 | CJ62: 213481 | CK62: LAMINA PILSEN FRASES TIPO D0.195 | CL62: 210654 | CM62: =VLOOKUP(CL62,$CI$2:$CK$20,3,0) -> LAMINA GEN LACADA TIPO D 0,195 | CN62: 210656 | CO62: 4918 | CR62: SE ENCUENTRA EN LA JAULA DE PRODUCTO BLOQUEADO
B63: RASSELSTEIN 0.17 | D63: =N54*1690 -> 0 | E63: 1.126 | F63: =D63*E63 -> 0 | H63: OCUPACION | M63: OCUPACION | R63: OCUPACION | W63: OCUPACION | AS63: N/A | AT63: SUXUN | AU63: SUXUN | AV63: SUXUN | BG63: SUXUN | CI63: 213351 | CJ63: 213349 | CK63: LAMINA NUESTRA SIEMBRA D 0.195 | CL63: 210656 | CM63: =VLOOKUP(CL63,$CI$2:$CK$20,3,0) -> LAMINA GEN BASE BLANCA LACADA TIPO D 0.195 | CN63: 0 | CO63: 0 | CR63: SE ENCUENTRA FRENTE A LA JAULA
F64: =F58+F60+F61+F63+F62 -> 567885.75 | AT64: 12 | CI64: 213325 | CJ64: 213322 | CK64: LAMINA PONY MALTA ANTOJOS 0.195 | CL64: 210656 | CM64: =VLOOKUP(CL64,$CI$2:$CK$20,3,0) -> LAMINA GEN BASE BLANCA LACADA TIPO D 0.195 | CN64: 0 | CO64: 0 | CR64: SE ENCUENTRA EN PROCESO DE RECUPERACION POR SIZING ALUMINIO
H65: NIVELES DE VARIACION X PAQUETES | M65: COBERTURA LAMINA TERMINADA EN DIAS | R65: SIMULACION DE INGRESO SOBRE CONSUMOS | CI65: 213637 | CJ65: 213635 | CK65: LAMINA AGUILA LGT PROMO ALFA TIP D 0.195 | CL65: 213677 | CM65: =VLOOKUP(CL65,$CI$2:$CK$20,3,0) -> LAMINA LACADA SIZING PROM TIPO D 0.195 | CN65: 0 | CO65: 0 | CR65: SE ENCUENTRA COMO LAMINA BLOQUEADA
B66: TOTAL TIPO D | D66: =D58+D60+D61+D63+D62 -> 441148 | H66: =D66-B82 -> 140256 | I66: =H66/1548 -> 90.604651 | J66: =H66/1680 -> 83.485714 | K66: =H66/1400 -> 100.18286 | M66: =T60/37500 -> 2.42432 | R66: INGRESOS | T66: PRODUCCION | CI66: 213679 | CJ66: 213676 | CK66: LAMINA CLUB ESMERALDA PROMOCION 0.195 | CL66: 213677 | CM66: =VLOOKUP(CL66,$CI$2:$CK$20,3,0) -> LAMINA LACADA SIZING PROM TIPO D 0.195 | CN66: 0 | CO66: 0 | CR66: SE ENCUENTRA EN LOS MODULOS DE LAMINA EN PROCESO
B67: TOTAL TIPO A | D67: =D59 -> 464750 | H67: LAMINAS | I67: PAQUETES | R67: 0 | T67: 259000 | CI67: 213732 | CJ67: 213731 | CK67: LAMINA COSTEÑA BACANA CENTRO TIPO D 0.195 | CL67: 210654 | CM67: =VLOOKUP(CL67,$CI$2:$CK$20,3,0) -> LAMINA GEN LACADA TIPO D 0,195 | CN67: 0 | CO67: 0
CI68: 213738 | CJ68: 213735 | CK68: LAMINA POKER RENOVACION | CL68: 210655 | CM68: =VLOOKUP(CL68,$CI$2:$CK$20,3,0) -> LAMINA GEN LACADA SIZING TIPO D 0,195 | CN68: 0 | CO68: 0
CI69: 213364 | CK69: LAMINA PILSENER ECUADOR TW TIPO D 0.195 | CL69: 210655 | CM69: =VLOOKUP(CL69,$CI$2:$CK$20,3,0) -> LAMINA GEN LACADA SIZING TIPO D 0,195 | CN69: 0 | CO69: 0
CI70: 213807 | CJ70: 213805 | CK70: LAMINA GENERICA PO ECUADOR CONVENCIONAL | CL70: 210655 | CM70: =VLOOKUP(CL70,$CI$2:$CK$20,3,0) -> LAMINA GEN LACADA SIZING TIPO D 0,195 | CN70: {=TRANSPOSE(CP7:CT7)} -> 0 | CO70: {=TRANSPOSE(CP8:CT8)} -> 0
CI71: 213239 | CJ71: 213302 | CK71: LAMINA PILSENER TIPO D 0.195 | CL71: 210655 | CM71: =VLOOKUP(CL71,$CI$2:$CK$20,3,0) -> LAMINA GEN LACADA SIZING TIPO D 0,195 | CN71: 213732 | CO71: 743
CI72: 213367 | CJ72: 213361 | CK72: LAMINA CLUB PREMIUM TW ECUADOR D0.195 | CL72: 210655 | CM72: =VLOOKUP(CL72,$CI$2:$CK$20,3,0) -> LAMINA GEN LACADA SIZING TIPO D 0,195 | CN72: 213637 | CO72: 974
B73: REGISTRO DE KARDEX INVENTARIO UNIDADES DE LAMINA | H73: REGISTRO DE KARDEX INVENTARIO KG DE LAMINA | R73: ESTADO AL 25-03-2026 | CI73: 206890 | CJ73: 202918 | CK73: LAMINA PONY MALTA TW | CL73: N/A | CM73: N/A | CN73: 213868 | CO73: 400
B74: INVENTARIO INIC DE LAMINA TIPO D | H74: INVENTARIO INIC DE LAMINA TIPO D | CI74: 202737 | CJ74: 208472 | CK74: LAMINA POKER 330/750R TIPO A LG | CL74: N/A | CM74: N/A | CN74: 211691 | CO74: 1847
B75: 222760 | H75: =B75*1.292 -> 287805.92 | R75: CAPACIDAD | T75: INVENTARIO | AP75: LAMINA TROQUELADA DESDE 10 PM | BC75: CANTIDAD TROQUELADORA | CI75: 207301 | CJ75: 202732 | CK75: LAMINA COSTEÑITA TIPO D | CL75: N/A | CM75: N/A | CN75: {=TRANSPOSE(CP10:CT10)} -> 0 | CO75: {=TRANSPOSE(CP11:CT11)} -> 0
B76: CONSUMOS | H76: CONSUMOS | R76: =1170*1500 -> 1755000 | T76: =+D66+R67-T67 -> 182148 | AP76: LINEA | AQ76: SKU | AR76: DESCRIPCION | AT76: CANTIDAD | AU76: SKU | AV76: DESCRIPCION | AX76: CANTIDAD | AY76: SKU | AZ76: DESCRIPCION | BB76: CANTIDAD | BC76: PAQUETES | CI76: 208477 | CJ76: 208472 | CK76: LAMINA POKER ROJA RET LG TIPO D 0,17 | CL76: N/A | CM76: N/A | CN76: 0 | CO76: 0
B77: =+(12*1548)+(15*1548)+(20*1548) -> 72756 | H77: =B77*1.29 -> 93855.24 | R77: =R76/1500 -> 1170 | T77: =+T76/1500 -> 121.432 | AP77: SACMI 1 | AR77: =IFERROR(VLOOKUP(AQ77,$CI:$CM,3,FALSE),"") | AV77: =IFERROR(VLOOKUP(AU77,$CI:$CM,3,FALSE),"") | AY77: 213996 | AZ77: =IFERROR(VLOOKUP(AY77,$CI:$CM,3,FALSE),"") -> LAMINA AGUILA MF 2026 UV TIPO D 0,195 | BB77: =671+1756+1612+1503 -> 5542 | CI77: 204388 | CJ77: 204340 | CK77: LAMINA REDDS TIPO D LG FASE II | CL77: N/A | CM77: N/A | CN77: 0 | CO77: 0
B78: BLOQUEADOS | H78: BLOQUEADOS | R78: =T76/R76 -> 0.10378803 | AP78: SACMI 2 | AR78: =IFERROR(VLOOKUP(AQ78,$CI:$CM,3,FALSE),"") | AV78: =IFERROR(VLOOKUP(AU78,$CI:$CM,3,FALSE),"") | AY78: 213637 | AZ78: =IFERROR(VLOOKUP(AY78,$CI:$CM,3,FALSE),"") -> LAMINA AGUILA LGT PROMO ALFA TIP D 0.195 | BB78: =1756+1380+270+1659 -> 5065 | CI78: 206458 | CK78: LAMINA CLUB PREMIUM RET TIPO D 0,17 ECU | CL78: N/A | CM78: N/A | CN78: 0 | CO78: 0
H79: =B79*1.292 -> 0 | R79: OCUPACION | AP79: SACMI 3 | AR79: =IFERROR(VLOOKUP(AQ79,$CI:$CM,3,FALSE),"") | AV79: =IFERROR(VLOOKUP(AU79,$CI:$CM,3,FALSE),"") | AY79: 213738 | AZ79: =IFERROR(VLOOKUP(AY79,$CI:$CM,3,FALSE),"") -> LAMINA POKER RENOVACION | BB79: =50+1533+1527+1552 -> 4662 | CI79: 209962 | CJ79: 209957 | CK79: LAMINA PACIFICO PERU | CL79: N/A | CM79: N/A | CN79: 0 | CO79: 0
B80: LLEGADAS | H80: LLEGADAS | AP80: SACMI 4 | AR80: =IFERROR(VLOOKUP(AQ80,$CI:$CM,3,FALSE),"") | AV80: =IFERROR(VLOOKUP(AU80,$CI:$CM,3,FALSE),"") | AY80: 212403 | AZ80: =IFERROR(VLOOKUP(AY80,$CI:$CM,3,FALSE),"") -> LAMINA COSTEÑA BACANA 2000 TP D 0.195 | BB80: =1372+1679+1441 -> 4492 | CI80: 210128 | CJ80: 210125 | CK80: LAMINA POKER BBC PURAMALTA TIPO D 0.17 | CL80: N/A | CM80: N/A | CN80: {=TRANSPOSE(CP13:CT13)} -> 210655 | CO80: {=TRANSPOSE(CP14:CT14)} -> 550
B81: =+(34*1548)+(32*1548)+(29*1680) -> 150888 | H81: =B81*1.292 -> 194947.3 | AP81: PRIMER CAMBIO DE MARCA | AU81: SEGUNDO CAMBIO DE MARCA | AY81: ACTUAL | CI81: 213174 | CJ81: 213172 | CK81: LAMINA SALVA VIDAS TIPO D0.17 | CL81: N/A | CM81: N/A | CN81: 0 | CO81: 0
B82: =SUM(B75+B81)-B77-B79 -> 300892 | H82: =B82*1.292 -> 388752.46 | CI82: 213240 | CJ82: 213302 | CK82: LAMINA PILSENER TIPO D 0.17 | CL82: N/A | CM82: N/A | CN82: 0 | CO82: 0
CI83: 213242 | CJ83: 213303 | CK83: LAMINA PILSENER LIGHT D 0.17 | CL83: N/A | CM83: N/A | CN83: 213677 | CO83: 16662
B84: INVENTARIO INICIAL LAMINA TIPO A | H84: INVENTARIO INICIAL LAMINA TIPO A | CI84: 213245 | CJ84: 213304 | CK84: LAMINA CLUB PREMIUM CLASICA TIPO D 0.17 | CL84: N/A | CM84: N/A | CN84: 0 | CO84: 0
B85: 0 | H85: =B85*1.014 -> 0 | CI85: 213241 | CJ85: 213303 | CK85: LAMINA PILSENER LIGHT D 0.195 | CL85: 210655 | CM85: =VLOOKUP(CL85,$CI$2:$CK$20,3,0) -> LAMINA GEN LACADA SIZING TIPO D 0,195 | CN85: {=TRANSPOSE(CP16:CT16)} -> 0 | CO85: {=TRANSPOSE(CP17:CT17)} -> 0
B86: CONSUMOS | H86: CONSUMOS | CI86: 213802 | CJ86: 213801 | CK86: LAMINA MCHELOB ULTRA NRB 330 TIPO D0.195 | CL86: 211749 | CM86: =VLOOKUP(CL86,$CI$2:$CK$20,3,0) -> LAM BASE BLANCA LACA OXY TIPO 0.195 | CN86: 0 | CO86: 0
H87: =B87*1.014 -> 0 | CI87: 213868 | CJ87: 213867 | CK87: LAMINA TAPA TEST CONV TIPO D0.195 | CL87: 210655 | CM87: =VLOOKUP(CL87,$CI$2:$CK$20,3,0) -> LAMINA GEN LACADA SIZING TIPO D 0,195 | CN87: 0 | CO87: 0
B88: BLOQUEADOS | H88: BLOQUEADOS | CI88: 213869 | CJ88: 213867 | CK88: LAMINA TAPA TEST UV TIPO D0.195 | CL88: 210655 | CM88: =VLOOKUP(CL88,$CI$2:$CK$20,3,0) -> LAMINA GEN LACADA SIZING TIPO D 0,195 | CN88: 0 | CO88: 0
B89: 0 | H89: =B89*1.014 -> 0 | CI89: 213885 | CJ89: 213883 | CK89: LAMINA TIPO D PILSENER MUNDIAL ECUADOR | CL89: 213677 | CM89: =VLOOKUP(CL89,$CI$2:$CK$20,3,0) -> LAMINA LACADA SIZING PROM TIPO D 0.195 | CN89: 212037 | CO89: 725
B90: LLEGADAS | H90: LLEGADAS | CI90: 213886 | CJ90: 213883 | CK90: LAMINA TIPO D PILSENER UV MUNDIAL EC | CL90: 213677 | CM90: =VLOOKUP(CL90,$CI$2:$CK$20,3,0) -> LAMINA LACADA SIZING PROM TIPO D 0.195 | CN90: {=TRANSPOSE(CP19:CX19)} -> 0 | CO90: {=TRANSPOSE(CP20:CX20)} -> 0
B91: =+(275*1690) -> 464750 | H91: =B91*1.014 -> 471256.5 | CI91: 211208 | CJ91: 202904 | CK91: LAMINA PILSEN GENERICA TIP D 0.195 | CL91: 210654 | CM91: =VLOOKUP(CL91,$CI$2:$CK$20,3,0) -> LAMINA GEN LACADA TIPO D 0,195 | CN91: 0 | CO91: 0
B92: =+(B85+B91)-B87-B89 -> 464750 | H92: =B92*1.014 -> 471256.5 | CI92: 213995 | CJ92: 213994 | CK92: LAMINA AGUILA MF 2026 CONV TIPO D 0,195 | CL92: 213677 | CM92: =VLOOKUP(CL92,$CI$2:$CK$20,3,0) -> LAMINA LACADA SIZING PROM TIPO D 0.195 | CN92: 0 | CO92: 0
CI93: 213996 | CJ93: 213994 | CK93: LAMINA AGUILA MF 2026 UV TIPO D 0,195 | CL93: 213677 | CM93: =VLOOKUP(CL93,$CI$2:$CK$20,3,0) -> LAMINA LACADA SIZING PROM TIPO D 0.195 | CN93: 211209 | CO93: 218
CN94: 206454 | CO94: 452
A95: 24 DIAS DE COBERTURA SEGÚN CAPACIDAD LAMINA TERMINADA | CN95: 206453 | CO95: 1176
CN96: 207544 | CO96: 4207
A97: 1 | CN97: 206455 | CO97: 6127
A98: 2 | CN98: 210654 | CO98: 9553
A99: 3 | CN99: =BW47 -> 210655 | CO99: =BZ47 -> 1700
A100: 4 | CN100: =BW48 -> 212403 | CO100: =BZ48 -> 313
...

Sheet DATA
A1: CODIGO | B1: CANTIDAD | C1: DESCCRIPCION | D1: PROVEEDOR | E1: MODULO
A2: ='MODELO LAYOUT'!$AI$15 -> 0 | B2: ='MODELO LAYOUT'!$AI$14 -> 0 | C2: ='MODELO LAYOUT'!AI18 -> 0 | D2: ='MODELO LAYOUT'!AI17 -> 0 | E2: ='MODELO LAYOUT'!AI9 -> 1
A3: ='MODELO LAYOUT'!$AJ$15 -> 0 | B3: ='MODELO LAYOUT'!$AJ$14 -> 0 | C3: ='MODELO LAYOUT'!AJ18 -> 0 | D3: ='MODELO LAYOUT'!AJ17 -> 0 | E3: ='MODELO LAYOUT'!AJ9 -> 2
A4: ='MODELO LAYOUT'!$AK$15 -> 0 | B4: ='MODELO LAYOUT'!$AK$14 -> 0 | C4: ='MODELO LAYOUT'!AK18 -> 0 | D4: ='MODELO LAYOUT'!AK17 -> 0 | E4: ='MODELO LAYOUT'!AK9 -> 3
A5: ='MODELO LAYOUT'!$AL$15 -> 0 | B5: ='MODELO LAYOUT'!$AL$14 -> 0 | C5: ='MODELO LAYOUT'!AL18 -> 0 | D5: ='MODELO LAYOUT'!AL17 -> 0 | E5: ='MODELO LAYOUT'!AL9 -> 4
A6: ='MODELO LAYOUT'!$AM$15 -> 0 | B6: ='MODELO LAYOUT'!$AM$14 -> 0 | C6: ='MODELO LAYOUT'!AM18 -> 0 | D6: ='MODELO LAYOUT'!AM17 -> 0 | E6: ='MODELO LAYOUT'!AM9 -> 5
A7: ='MODELO LAYOUT'!$AN$15 -> 0 | B7: ='MODELO LAYOUT'!$AN$14 -> 0 | C7: ='MODELO LAYOUT'!AN18 -> 0 | D7: ='MODELO LAYOUT'!AN17 -> 0 | E7: ='MODELO LAYOUT'!AN9 -> 6
A8: ='MODELO LAYOUT'!$AO$15 -> 0 | B8: ='MODELO LAYOUT'!$AO$14 -> 0 | C8: ='MODELO LAYOUT'!AO18 -> 0 | D8: ='MODELO LAYOUT'!AO1 -> 0 | E8: ='MODELO LAYOUT'!AO9 -> 7
A9: ='MODELO LAYOUT'!$AP$15 -> 0 | B9: ='MODELO LAYOUT'!$AP$14 -> 0 | C9: ='MODELO LAYOUT'!AP18 -> 0 | D9: ='MODELO LAYOUT'!AP17 -> 0 | E9: ='MODELO LAYOUT'!AP9 -> 8
A10: ='MODELO LAYOUT'!$AQ$15 -> 0 | B10: ='MODELO LAYOUT'!$AQ$14 -> 0 | C10: ='MODELO LAYOUT'!AQ18 -> 0 | D10: ='MODELO LAYOUT'!AQ17 -> 0 | E10: ='MODELO LAYOUT'!AQ9 -> 9
A11: ='MODELO LAYOUT'!$AR$15 -> 0 | B11: ='MODELO LAYOUT'!$AR$14 -> 0 | C11: ='MODELO LAYOUT'!AR18 -> 0 | D11: ='MODELO LAYOUT'!AR17 -> 0 | E11: ='MODELO LAYOUT'!AR9 -> 10
A12: ='MODELO LAYOUT'!$AS$15 -> 0 | B12: ='MODELO LAYOUT'!$AS$14 -> 0 | C12: ='MODELO LAYOUT'!AS18 -> 0 | D12: ='MODELO LAYOUT'!AS17 -> 0 | E12: ='MODELO LAYOUT'!AS9 -> 11
A13: ='MODELO LAYOUT'!$AT$15 -> 0 | B13: ='MODELO LAYOUT'!$AT$14 -> 0 | C13: ='MODELO LAYOUT'!AT18 -> 0 | D13: ='MODELO LAYOUT'!AT17 -> 0 | E13: ='MODELO LAYOUT'!AT9 -> 12
A14: ='MODELO LAYOUT'!$AU$15 -> 213677 | B14: ='MODELO LAYOUT'!$AU$14 -> 13932 | C14: ='MODELO LAYOUT'!AU18 -> 0 | D14: ='MODELO LAYOUT'!AU17 -> 0 | E14: ='MODELO LAYOUT'!AU9 -> 13
A15: ='MODELO LAYOUT'!$AV$15 -> 212037 | B15: ='MODELO LAYOUT'!$AV$14 -> 640 | C15: ='MODELO LAYOUT'!AV18 -> CLUB COLOMBIA MALA IMPRESION | D15: ='MODELO LAYOUT'!AV17 -> SUXUN | E15: ='MODELO LAYOUT'!AV9 -> 14
A16: ='MODELO LAYOUT'!$AW$15 -> 211671 | B16: ='MODELO LAYOUT'!$AW$14 -> 2313 | C16: ='MODELO LAYOUT'!AW18 -> COLA Y POLA | D16: ='MODELO LAYOUT'!AW17 -> JINTAI | E16: ='MODELO LAYOUT'!AW9 -> 15
A17: ='MODELO LAYOUT'!$AX$15 -> 211749 | B17: ='MODELO LAYOUT'!$AX$14 -> 2955 | C17: ='MODELO LAYOUT'!AX18 -> BASE BEIGE | D17: ='MODELO LAYOUT'!AX17 -> SUXUN | E17: ='MODELO LAYOUT'!AX9 -> 16
A18: ='MODELO LAYOUT'!$AY$15 -> 210655 | B18: ='MODELO LAYOUT'!$AY$14 -> 1694 | C18: ='MODELO LAYOUT'!AY18 -> PILSENER LACADA + SIZING | D18: ='MODELO LAYOUT'!AY17 -> SUXUN | E18: ='MODELO LAYOUT'!AY9 -> 17
A19: ='MODELO LAYOUT'!$AZ$15 -> 213239 | B19: ='MODELO LAYOUT'!$AZ$14 -> 371 | C19: ='MODELO LAYOUT'!AZ18 -> PILSENER | D19: ='MODELO LAYOUT'!AZ17 -> SUXUN | E19: ='MODELO LAYOUT'!AZ9 -> 18
A20: ='MODELO LAYOUT'!$BA$15 -> 213995 | B20: ='MODELO LAYOUT'!$BA$14 -> 310 | C20: ='MODELO LAYOUT'!BA18 -> 0 | D20: ='MODELO LAYOUT'!BA17 -> 0 | E20: ='MODELO LAYOUT'!BA9 -> 19
A21: ='MODELO LAYOUT'!$BB$15 -> 212315 | B21: ='MODELO LAYOUT'!$BB$14 -> 140 | C21: ='MODELO LAYOUT'!BB18 -> COSTEÑITA CB | D21: ='MODELO LAYOUT'!BB17 -> STEEL FORCE | E21: ='MODELO LAYOUT'!BB9 -> 20
A22: ='MODELO LAYOUT'!$BC$15 -> 210760 | B22: ='MODELO LAYOUT'!$BC$14 -> 165 | C22: ='MODELO LAYOUT'!BC18 -> ÁGUILA ORIGINAL | D22: ='MODELO LAYOUT'!BC17 -> STEEL FORCE | E22: ='MODELO LAYOUT'!BC9 -> 21
A23: ='MODELO LAYOUT'!$AI$21 -> 0 | B23: ='MODELO LAYOUT'!AI$20 -> 0 | C23: ='MODELO LAYOUT'!AI24 -> 0 | D23: ='MODELO LAYOUT'!AI23 | E23: ='MODELO LAYOUT'!AI25 -> 0
A24: ='MODELO LAYOUT'!$AJ$21 -> 0 | B24: ='MODELO LAYOUT'!$AJ$20 -> 0 | C24: ='MODELO LAYOUT'!AJ24 -> 0 | D24: ='MODELO LAYOUT'!AJ23 -> 0 | E24: ='MODELO LAYOUT'!AJ25 -> 0
A25: ='MODELO LAYOUT'!$AK$21 -> 0 | B25: ='MODELO LAYOUT'!$AK$20 -> 0 | C25: ='MODELO LAYOUT'!AK24 -> 0 | D25: ='MODELO LAYOUT'!AK23 -> 0 | E25: ='MODELO LAYOUT'!AK25 -> 0
A26: ='MODELO LAYOUT'!$AL$21 -> 0 | B26: ='MODELO LAYOUT'!$AL$20 -> 0 | C26: ='MODELO LAYOUT'!AL24 -> 0 | D26: ='MODELO LAYOUT'!AL23 -> 0 | E26: ='MODELO LAYOUT'!AL25 -> 0
A27: ='MODELO LAYOUT'!$AM$21 -> 0 | B27: ='MODELO LAYOUT'!$AM$20 -> 0 | C27: ='MODELO LAYOUT'!AM24 -> 0 | D27: ='MODELO LAYOUT'!AM23 -> 0 | E27: ='MODELO LAYOUT'!AM25 -> 0
A28: ='MODELO LAYOUT'!AN$21 -> 0 | B28: ='MODELO LAYOUT'!$AN$20 -> 0 | C28: ='MODELO LAYOUT'!AN24 -> 0 | D28: ='MODELO LAYOUT'!AN23 -> 0 | E28: ='MODELO LAYOUT'!AN25 -> 0
A29: ='MODELO LAYOUT'!$AO$21 -> 0 | B29: ='MODELO LAYOUT'!$AO$20 -> 0 | C29: ='MODELO LAYOUT'!AO24 -> 0 | D29: ='MODELO LAYOUT'!AO23 -> 0 | E29: ='MODELO LAYOUT'!AO25 -> 0
A30: ='MODELO LAYOUT'!$AP$21 -> 0 | B30: ='MODELO LAYOUT'!$AP$20 -> 0 | C30: ='MODELO LAYOUT'!AP24 -> 0 | D30: ='MODELO LAYOUT'!AP23 -> 0 | E30: ='MODELO LAYOUT'!AP25 -> 0
A31: ='MODELO LAYOUT'!$AQ$21 -> 0 | B31: ='MODELO LAYOUT'!$AQ$20 -> 0 | C31: ='MODELO LAYOUT'!AQ24 -> 0 | D31: ='MODELO LAYOUT'!AQ23 -> 0 | E31: ='MODELO LAYOUT'!AQ25 -> 0
A32: ='MODELO LAYOUT'!$AR$21 -> 0 | B32: ='MODELO LAYOUT'!$AR$20 -> 0 | C32: ='MODELO LAYOUT'!AR24 -> 0 | D32: ='MODELO LAYOUT'!AR23 -> 0 | E32: ='MODELO LAYOUT'!AR25 -> 0
A33: ='MODELO LAYOUT'!$AS$21 -> 0 | B33: ='MODELO LAYOUT'!$AS$20 -> 0 | C33: ='MODELO LAYOUT'!AS24 -> 0 | D33: ='MODELO LAYOUT'!AS23 -> 0 | E33: ='MODELO LAYOUT'!AS25 -> 0
A34: ='MODELO LAYOUT'!$AT$21 -> 0 | B34: ='MODELO LAYOUT'!$AT$20 -> 0 | C34: ='MODELO LAYOUT'!AT24 -> 0 | D34: ='MODELO LAYOUT'!AT23 -> 0 | E34: ='MODELO LAYOUT'!AT25 -> 0
A35: ='MODELO LAYOUT'!$AU$21 -> 0 | B35: ='MODELO LAYOUT'!$AU$20 -> 0 | C35: ='MODELO LAYOUT'!AU24 -> 0 | D35: ='MODELO LAYOUT'!AU23 -> 0 | E35: ='MODELO LAYOUT'!AU25 -> 0
A36: ='MODELO LAYOUT'!$AV$21 -> 0 | B36: ='MODELO LAYOUT'!$AV$20 -> 0 | C36: ='MODELO LAYOUT'!AV24 -> 0 | D36: ='MODELO LAYOUT'!AV23 -> 0 | E36: ='MODELO LAYOUT'!AV25 -> 0
A37: ='MODELO LAYOUT'!$AW$21 -> 212037 | B37: ='MODELO LAYOUT'!$AW$20 -> 480 | C37: ='MODELO LAYOUT'!AW24 -> CLUB | D37: ='MODELO LAYOUT'!AW23 -> SUXUN | E37: ='MODELO LAYOUT'!AW25 -> 0
A38: ='MODELO LAYOUT'!$AX$21 -> 0 | B38: ='MODELO LAYOUT'!$AX$20 -> 0 | C38: ='MODELO LAYOUT'!AX24 -> 0 | D38: ='MODELO LAYOUT'!AX23 -> 0 | E38: ='MODELO LAYOUT'!AX25 -> 0
A39: ='MODELO LAYOUT'!$AY$21 -> 207544 | B39: ='MODELO LAYOUT'!$AY$20 -> 1690 | C39: ='MODELO LAYOUT'!AY24 -> LACADA PARA POKER | D39: ='MODELO LAYOUT'!AY23 -> NIPÓN | E39: ='MODELO LAYOUT'!AY25 -> 0
A40: ='MODELO LAYOUT'!$AZ$21 -> 210656 | B40: ='MODELO LAYOUT'!$AZ$20 -> 4918 | C40: ='MODELO LAYOUT'!AZ24 -> BASE BLANCA PONY | D40: ='MODELO LAYOUT'!AZ23 -> STEEL FORCE | E40: ='MODELO LAYOUT'!AZ25 -> 0
A41: ='MODELO LAYOUT'!$BA$21 -> 0 | B41: ='MODELO LAYOUT'!$BA$20 -> 0 | C41: ='MODELO LAYOUT'!BA24 -> 0 | D41: ='MODELO LAYOUT'!BA23 -> 0 | E41: ='MODELO LAYOUT'!BA25 -> 0
A42: ='MODELO LAYOUT'!$BB$21 -> 0 | B42: ='MODELO LAYOUT'!$BB$20 -> 0 | C42: ='MODELO LAYOUT'!BB24 -> 0 | D42: ='MODELO LAYOUT'!BB23 -> 0 | E42: ='MODELO LAYOUT'!BB25 -> 0
A43: ='MODELO LAYOUT'!$BC$21 -> 0 | B43: ='MODELO LAYOUT'!$BC$20 -> 0 | C43: ='MODELO LAYOUT'!BC24 -> 0 | D43: ='MODELO LAYOUT'!BC23 -> 0 | E43: ='MODELO LAYOUT'!BC25 -> 0
A44: ='MODELO LAYOUT'!$BE$15 -> 0 | B44: ='MODELO LAYOUT'!$BE$14 -> 0 | C44: ='MODELO LAYOUT'!BE18 -> 0 | D44: ='MODELO LAYOUT'!BE17 -> 0 | E44: ='MODELO LAYOUT'!BE9 -> 22
A45: ='MODELO LAYOUT'!$BF$15 -> 0 | B45: ='MODELO LAYOUT'!$BF$14 -> 0 | C45: ='MODELO LAYOUT'!BF18 -> 0 | D45: ='MODELO LAYOUT'!BF17 -> 0 | E45: ='MODELO LAYOUT'!BF9 -> 23
A46: ='MODELO LAYOUT'!$BG$15 -> 0 | B46: ='MODELO LAYOUT'!$BG$14 -> 0 | C46: ='MODELO LAYOUT'!BG18 -> 0 | D46: ='MODELO LAYOUT'!BG17 -> 0 | E46: ='MODELO LAYOUT'!BG9 -> 24
A47: ='MODELO LAYOUT'!$BE$21 -> 0 | B47: ='MODELO LAYOUT'!$BE$20 -> 0 | C47: ='MODELO LAYOUT'!BE24 -> 0 | D47: ='MODELO LAYOUT'!BE23 -> 0 | E47: ='MODELO LAYOUT'!BE25 -> 0
A48: ='MODELO LAYOUT'!$BF$21 -> 0 | B48: ='MODELO LAYOUT'!$BF$20 -> 0 | C48: ='MODELO LAYOUT'!BF24 -> 0 | D48: ='MODELO LAYOUT'!BF23 -> 0 | E48: ='MODELO LAYOUT'!BF25 -> 0
A49: ='MODELO LAYOUT'!$BG$21 -> 0 | B49: ='MODELO LAYOUT'!$BG$20 -> 0 | C49: ='MODELO LAYOUT'!BG24 -> 0 | D49: ='MODELO LAYOUT'!BG23 -> 0 | E49: ='MODELO LAYOUT'!BG25 -> 0
A50: ='MODELO LAYOUT'!$BJ$19 -> 0 | B50: ='MODELO LAYOUT'!$BJ$18 -> 0 | C50: ='MODELO LAYOUT'!BJ22 -> 0 | D50: ='MODELO LAYOUT'!BJ21 -> 0 | E50: ='MODELO LAYOUT'!BJ9 -> 25
A51: ='MODELO LAYOUT'!$BK$19 -> 213732 | B51: ='MODELO LAYOUT'!$BK$18 -> 743 | C51: ='MODELO LAYOUT'!BK22 -> COSTEÑA BACANA CENTRO | D51: ='MODELO LAYOUT'!BK21 -> STEEL FORCE | E51: ='MODELO LAYOUT'!BK9 -> 26
A52: ='MODELO LAYOUT'!$BL$19 -> 213637 | B52: ='MODELO LAYOUT'!$BL$18 -> 974 | C52: ='MODELO LAYOUT'!BL22 -> LIGHT | D52: ='MODELO LAYOUT'!BL21 -> STEEL FORCE | E52: ='MODELO LAYOUT'!BL9 -> 27
A53: ='MODELO LAYOUT'!$BM$19 -> 213868 | B53: ='MODELO LAYOUT'!$BM$18 -> 400 | C53: ='MODELO LAYOUT'!BM22 -> TEST | D53: ='MODELO LAYOUT'!BM21 -> JINTAI | E53: ='MODELO LAYOUT'!BM9 -> 28
A54: ='MODELO LAYOUT'!$BN$19 -> 211691 | B54: ='MODELO LAYOUT'!$BN$18 -> 1847 | C54: ='MODELO LAYOUT'!BN22 -> NATIVA | D54: ='MODELO LAYOUT'!BN21 -> JINTAI | E54: ='MODELO LAYOUT'!BN9 -> 29
A55: ='MODELO LAYOUT'!$BJ$25 -> 0 | B55: ='MODELO LAYOUT'!$BJ$24 -> 0 | C55: ='MODELO LAYOUT'!BJ28 -> 0 | D55: ='MODELO LAYOUT'!BJ27 -> 0 | E55: ='MODELO LAYOUT'!BJ29 -> 0
A56: ='MODELO LAYOUT'!$BK$25 -> 0 | B56: ='MODELO LAYOUT'!$BK$24 -> 0 | C56: ='MODELO LAYOUT'!BK28 -> 0 | D56: ='MODELO LAYOUT'!BK27 -> 0 | E56: ='MODELO LAYOUT'!BK29 -> 0
A57: ='MODELO LAYOUT'!$BL$25 -> 0 | B57: ='MODELO LAYOUT'!$BL$24 -> 0 | C57: ='MODELO LAYOUT'!BL28 -> 0 | D57: ='MODELO LAYOUT'!BL27 -> 0 | E57: ='MODELO LAYOUT'!BL29 -> 0
A58: ='MODELO LAYOUT'!$BM$25 -> 0 | B58: ='MODELO LAYOUT'!$BM$24 -> 0 | C58: ='MODELO LAYOUT'!BM28 -> 0 | D58: ='MODELO LAYOUT'!BM27 -> 0 | E58: ='MODELO LAYOUT'!BM29 -> 0
A59: ='MODELO LAYOUT'!$BN$25 -> 0 | B59: ='MODELO LAYOUT'!$BN$24 -> 0 | C59: ='MODELO LAYOUT'!BN28 -> 0 | D59: ='MODELO LAYOUT'!BN27 -> 0 | E59: ='MODELO LAYOUT'!BN29 -> 0
A60: ='MODELO LAYOUT'!$BU$19 -> 210655 | B60: ='MODELO LAYOUT'!$BU$18 -> 550 | C60: ='MODELO LAYOUT'!BU22 -> LACADA ALUMINAZADA PARA ÁGUILA | D60: ='MODELO LAYOUT'!BU21 -> SUXUN | E60: ='MODELO LAYOUT'!BU9 -> 32
A61: ='MODELO LAYOUT'!$BV$19 -> 0 | B61: ='MODELO LAYOUT'!$BV$18 -> 0 | C61: ='MODELO LAYOUT'!BV22 -> 0 | D61: ='MODELO LAYOUT'!BV21 -> 0 | E61: ='MODELO LAYOUT'!BV9 -> 33
A62: ='MODELO LAYOUT'!$BW$19 -> 0 | B62: ='MODELO LAYOUT'!$BW$18 -> 0 | C62: ='MODELO LAYOUT'!BW22 -> 0 | D62: ='MODELO LAYOUT'!BW21 -> 0 | E62: ='MODELO LAYOUT'!BW9 -> 34
A63: ='MODELO LAYOUT'!$BX$19 -> 213677 | B63: ='MODELO LAYOUT'!$BX$18 -> 16662 | C63: ='MODELO LAYOUT'!BX22 -> BASE DORADA | D63: ='MODELO LAYOUT'!BX21 -> SUXUN | E63: ='MODELO LAYOUT'!BX9 -> 35
A64: ='MODELO LAYOUT'!$BY$19 -> 0 | B64: ='MODELO LAYOUT'!$BY$18 -> 0 | C64: ='MODELO LAYOUT'!BY22 -> 0 | D64: ='MODELO LAYOUT'!BY21 -> 0 | E64: ='MODELO LAYOUT'!BY9 -> 36
A65: ='MODELO LAYOUT'!$BU$25 -> 0 | B65: ='MODELO LAYOUT'!$BU$24 -> 0 | C65: ='MODELO LAYOUT'!BU28 -> 0 | D65: ='MODELO LAYOUT'!BU27 -> 0 | E65: ='MODELO LAYOUT'!BU29 -> 0
A66: ='MODELO LAYOUT'!$BV$25 -> 0 | B66: ='MODELO LAYOUT'!$BV$24 -> 0 | C66: ='MODELO LAYOUT'!BV28 -> 0 | D66: ='MODELO LAYOUT'!BV27 -> 0 | E66: ='MODELO LAYOUT'!BV29 -> 0
A67: ='MODELO LAYOUT'!$BW$25 -> 0 | B67: ='MODELO LAYOUT'!$BW$24 -> 0 | C67: ='MODELO LAYOUT'!BW28 -> 0 | D67: ='MODELO LAYOUT'!BW27 -> 0 | E67: ='MODELO LAYOUT'!BW29 -> 0
A68: ='MODELO LAYOUT'!$BX$25 -> 0 | B68: ='MODELO LAYOUT'!$BX$24 -> 0 | C68: ='MODELO LAYOUT'!BX28 -> 0 | D68: ='MODELO LAYOUT'!BX27 -> 0 | E68: ='MODELO LAYOUT'!BX29 -> 0
A69: ='MODELO LAYOUT'!$BY$25 -> 212037 | B69: ='MODELO LAYOUT'!$BY$24 -> 725 | C69: ='MODELO LAYOUT'!BY28 -> TEST CON AMARILLOS | D69: ='MODELO LAYOUT'!BY27 -> SUXUN | E69: ='MODELO LAYOUT'!BY29 -> 0
A70: ='MODELO LAYOUT'!$BQ$32 -> 0 | B70: ='MODELO LAYOUT'!$BQ$31 -> 0 | C70: ='MODELO LAYOUT'!BQ35 -> 0 | D70: ='MODELO LAYOUT'!BQ34 -> 0 | E70: ='MODELO LAYOUT'!BQ30 -> 0
A71: ='MODELO LAYOUT'!$BR$32 -> 0 | B71: ='MODELO LAYOUT'!$BR$31 -> 0 | C71: ='MODELO LAYOUT'!BR35 -> 0 | D71: ='MODELO LAYOUT'!BR34 -> 0 | E71: ='MODELO LAYOUT'!BR30 -> 0
A72: ='MODELO LAYOUT'!$BS$32 -> 0 | B72: ='MODELO LAYOUT'!$BS$31 -> 0 | C72: ='MODELO LAYOUT'!BS35 -> 0 | D72: ='MODELO LAYOUT'!BS34 -> 0 | E72: ='MODELO LAYOUT'!BS30 -> 0
A73: ='MODELO LAYOUT'!$BT$32 -> 211209 | B73: ='MODELO LAYOUT'!$BT$31 -> 218 | C73: ='MODELO LAYOUT'!BT35 -> LACA + BASE BLANCA RASELSTEIN | D73: ='MODELO LAYOUT'!BT34 -> STEEL FORCE | E73: ='MODELO LAYOUT'!BT30 -> 0
A74: ='MODELO LAYOUT'!$BU$32 -> 206454 | B74: ='MODELO LAYOUT'!$BU$31 -> 452 | C74: ='MODELO LAYOUT'!BU35 -> LACA + BASE BLANCA RASELSTEIN | D74: ='MODELO LAYOUT'!BU34 -> STEEL FORCE | E74: ='MODELO LAYOUT'!BU30 -> 0
A75: ='MODELO LAYOUT'!$BV$32 -> 206453 | B75: ='MODELO LAYOUT'!$BV$31 -> 1176 | C75: ='MODELO LAYOUT'!BV35 -> LACA 0.17 | D75: ='MODELO LAYOUT'!BV34 -> RASSELSTEIN | E75: ='MODELO LAYOUT'!BV30 -> 0
A76: ='MODELO LAYOUT'!$BW$32 -> 207544 | B76: ='MODELO LAYOUT'!$BW$31 -> 4207 | C76: ='MODELO LAYOUT'!BW35 -> LACADA + SIZING | D76: ='MODELO LAYOUT'!BW34 -> NIPÓN | E76: ='MODELO LAYOUT'!BW30 -> 0
A77: ='MODELO LAYOUT'!$BX$32 -> 206455 | B77: ='MODELO LAYOUT'!$BX$31 -> 6127 | C77: ='MODELO LAYOUT'!BX35 -> 0.17 LACADA +SIZING | D77: ='MODELO LAYOUT'!BX34 -> RASSELSTEIN | E77: ='MODELO LAYOUT'!BX30 -> 0
A78: ='MODELO LAYOUT'!$BY$32 -> 210654 | B78: ='MODELO LAYOUT'!$BY$31 -> 9553 | C78: ='MODELO LAYOUT'!BY35 -> OXIDADA | D78: ='MODELO LAYOUT'!BY34 -> JINTAI | E78: ='MODELO LAYOUT'!BY30 -> 0
A79: ='MODELO LAYOUT'!$BW$47 -> 210655 | B79: ='MODELO LAYOUT'!$BZ$47 -> 1700 | C79: ='MODELO LAYOUT'!BX47 -> LAMINA GEN LACADA SIZING TIPO D 0,195 | D79: ='MODELO LAYOUT'!BZ59 -> N/A | E79: ='MODELO LAYOUT'!BV47 -> DEFECTOS | BB79: {=+((169*11000)/667)+DATA!A:B} -> #VALUE!
A80: ='MODELO LAYOUT'!$BW$48 -> 212403 | B80: ='MODELO LAYOUT'!$BZ$48 -> 313 | C80: ='MODELO LAYOUT'!BX48 -> LAMINA COSTEÑA BACANA 2000 TP D 0.195 | D80: ='MODELO LAYOUT'!BZ59 -> N/A | E80: ='MODELO LAYOUT'!BV48 -> DEFECTOS
A81: ='MODELO LAYOUT'!$BW$49 -> 212127 | B81: ='MODELO LAYOUT'!$BZ$49 -> 887 | C81: ='MODELO LAYOUT'!BX49 -> LAMINA YO ME CUIDO PERU ST TIPO D 0.195 | D81: ='MODELO LAYOUT'!BZ59 -> N/A | E81: ='MODELO LAYOUT'!BV49 -> DEFECTOS
A82: ='MODELO LAYOUT'!$BW$50 -> 212127 | B82: ='MODELO LAYOUT'!$BZ$50 -> 1216 | C82: ='MODELO LAYOUT'!BX50 -> LAMINA YO ME CUIDO PERU ST TIPO D 0.195 | D82: ='MODELO LAYOUT'!BZ59 -> N/A | E82: ='MODELO LAYOUT'!BV50 -> DEFECTOS
A83: ='MODELO LAYOUT'!$BW$51 -> 213637 | B83: ='MODELO LAYOUT'!$BZ$51 -> 733 | C83: ='MODELO LAYOUT'!BX51 -> LAMINA AGUILA LGT PROMO ALFA TIP D 0.195 | D83: ='MODELO LAYOUT'!BZ59 -> N/A | E83: ='MODELO LAYOUT'!BV51 -> DEFECTOS
A84: ='MODELO LAYOUT'!$BW$52 -> 210655 | B84: ='MODELO LAYOUT'!$BZ$52 -> 540 | C84: ='MODELO LAYOUT'!BX52 -> LAMINA GEN LACADA SIZING TIPO D 0,195 | D84: ='MODELO LAYOUT'!BZ59 -> N/A | E84: ='MODELO LAYOUT'!BV52 -> DEFECTOS
A85: ='MODELO LAYOUT'!$BW$53 -> 213637 | B85: ='MODELO LAYOUT'!$BZ$53 -> 1181 | C85: ='MODELO LAYOUT'!BX53 -> LAMINA AGUILA LGT PROMO ALFA TIP D 0.195 | D85: ='MODELO LAYOUT'!BZ59 -> N/A | E85: ='MODELO LAYOUT'!BV53 -> DEFECTOS
A86: ='MODELO LAYOUT'!$BW$54 -> 213637 | B86: ='MODELO LAYOUT'!$BZ$54 -> 690 | C86: ='MODELO LAYOUT'!BX54 -> LAMINA AGUILA LGT PROMO ALFA TIP D 0.195 | D86: ='MODELO LAYOUT'!BZ59 -> N/A | E86: ='MODELO LAYOUT'!BV54 -> DEFECTOS
A87: ='MODELO LAYOUT'!$BW$55 -> 213738 | B87: ='MODELO LAYOUT'!$BZ$55 -> 1460 | C87: ='MODELO LAYOUT'!BX55 -> LAMINA POKER RENOVACION | D87: ='MODELO LAYOUT'!BZ59 -> N/A | E87: ='MODELO LAYOUT'!BV55 -> DEFECTOS
A88: ='MODELO LAYOUT'!$AS$55 -> 0 | B88: ='MODELO LAYOUT'!$AS$54 -> 0 | C88: ='MODELO LAYOUT'!AS56 | D88: ='MODELO LAYOUT'!AS57 -> 0 | E88: ='MODELO LAYOUT'!AS46 -> 20
A89: ='MODELO LAYOUT'!$AT$55 -> 0 | B89: ='MODELO LAYOUT'!$AT$54 -> 0 | C89: ='MODELO LAYOUT'!AT56 | D89: ='MODELO LAYOUT'!AT57 -> 0 | E89: ='MODELO LAYOUT'!AT46 -> 19
A90: ='MODELO LAYOUT'!$AU$55 -> 207301 | B90: ='MODELO LAYOUT'!$AU$54 -> 7348 | C90: ='MODELO LAYOUT'!AU56 -> LAMINA COSTEÑITA TIPO D | D90: ='MODELO LAYOUT'!AU57 -> N/A | E90: ='MODELO LAYOUT'!AU46 -> 18
A91: ='MODELO LAYOUT'!$AV$55 -> 212604 | B91: ='MODELO LAYOUT'!$AV$54 -> 2413 | C91: ='MODELO LAYOUT'!AV56 -> LAMINA COSTEÑA ROJA TIPO D0.195 | D91: ='MODELO LAYOUT'!AV57 -> JINTAI | E91: ='MODELO LAYOUT'!AV46 -> 17
A92: ='MODELO LAYOUT'!$AS$61 -> 206458 | B92: ='MODELO LAYOUT'!$AS$60 -> 4693 | C92: ='MODELO LAYOUT'!AS62 -> LAMINA CLUB PREMIUM RET TIPO D 0,17 ECU | D92: ='MODELO LAYOUT'!AS63 -> N/A | E92: ='MODELO LAYOUT'!AS59 -> 23
A93: ='MODELO LAYOUT'!$AT$61 -> 210760 | B93: ='MODELO LAYOUT'!$AT$60 -> 4760 | C93: ='MODELO LAYOUT'!AT62 -> LAMINA AGUILA AZUL TIPO D 0.195 | D93: ='MODELO LAYOUT'!AT63 -> SUXUN | E93: ='MODELO LAYOUT'!AT59 -> 21
A94: ='MODELO LAYOUT'!$AU$61 -> 213637 | B94: ='MODELO LAYOUT'!$AU$60 -> 1037 | C94: ='MODELO LAYOUT'!AU62 -> LAMINA AGUILA LGT PROMO ALFA TIP D 0.195 | D94: ='MODELO LAYOUT'!AU63 -> SUXUN | E94: ='MODELO LAYOUT'!AU59 -> 20
A95: ='MODELO LAYOUT'!$AV$61 -> 213367 | B95: ='MODELO LAYOUT'!$AV$60 -> 520 | C95: ='MODELO LAYOUT'!AV62 -> LAMINA CLUB PREMIUM TW ECUADOR D0.195 | D95: ='MODELO LAYOUT'!AV63 -> SUXUN | E95: ='MODELO LAYOUT'!AV59 -> 19
A96: ='MODELO LAYOUT'!$AX$47 -> 206890 | B96: ='MODELO LAYOUT'!$AZ$47 -> 1692 | C96: ='MODELO LAYOUT'!AY47 -> LAMINA PONY MALTA TW | D96: ='MODELO LAYOUT'!BZ59 -> N/A | E96: ='MODELO LAYOUT'!AX46 -> M-M
A97: ='MODELO LAYOUT'!$AX$48 -> 210128 | B97: ='MODELO LAYOUT'!$AZ$48 -> 1630 | C97: ='MODELO LAYOUT'!AY48 -> LAMINA POKER BBC PURAMALTA TIPO D 0.17 | D97: ='MODELO LAYOUT'!BZ59 -> N/A | E97: ='MODELO LAYOUT'!AX46 -> M-M
A98: ='MODELO LAYOUT'!$AX$49 -> 209962 | B98: ='MODELO LAYOUT'!$AZ$49 -> 500 | C98: ='MODELO LAYOUT'!AY49 -> LAMINA PACIFICO PERU | D98: ='MODELO LAYOUT'!BZ59 -> N/A | E98: ='MODELO LAYOUT'!AX46 -> M-M
A99: ='MODELO LAYOUT'!$AX$50 -> 204388 | B99: ='MODELO LAYOUT'!$AZ$50 -> 43 | C99: ='MODELO LAYOUT'!AY50 -> LAMINA REDDS TIPO D LG FASE II | D99: ='MODELO LAYOUT'!BZ59 -> N/A | E99: ='MODELO LAYOUT'!AX46 -> M-M
A100: ='MODELO LAYOUT'!$AX$51 -> 202737 | B100: ='MODELO LAYOUT'!$AZ$51 -> 2854 | C100: ='MODELO LAYOUT'!AY51 -> LAMINA POKER 330/750R TIPO A LG | D100: ='MODELO LAYOUT'!BZ59 -> N/A | E100: ='MODELO LAYOUT'!AX46 -> M-M
...
